Workbook

Sheet Resumen
A1: WKH-2026 · Entrega N2 — Resumen y controles de consistencia
A2: Implementación de la plataforma WorkHub, sede Catalinas · Grupo 1 · Docente: Mag. Ezequiel Pietracupa
A4: Indicador | B4: Valor | C4: Nota
A5: Duración de la red (días hábiles) | B5: =FinRed -> 140 | C5: La red incluye la ventana de balances como actividad R-3.
A6: Duración del calendario (días hábiles, H-0 a fin del plan) | B6: =NETWORKDAYS(InicioProyecto,Tareas!N11,Feriados) -> 140 | C6: Debe coincidir con la duración de la red.
A7: Control: red = calendario | B7: =IF(B5=B6,"OK","REVISAR") -> OK
A8: Fin del plan | B8: =Tareas!N11 -> 46507 | C8: H-7: 30/04/2027.
A9: Duración de la tarea 1.5 (listado = Gantt = AON) | B9: =Tareas!D10 -> 132 | C9: Una sola celda alimenta las tres vistas.
A10: Tareas del listado (incluye 1.5 y 1.6) | B10: =COUNTIF(Tareas!A6:A37,"<>R-3") -> 31 | C10: 31 paquetes de trabajo de la EDT ↔ 31 tareas. R-3 es la restricción externa.
A11: Tareas críticas (holgura 0) | B11: =COUNTIF(Tareas!L6:L37,"Sí") -> 6 | C11: R-3 → 5.3 → 5.4 → (5.5 y 5.6) → 1.6.
A12: Holgura de la ruta previa a la ventana (piloto 5.2), días hábiles | B12: =Tareas!K32 -> 8 | C12: Es la holgura contra el inicio de la ventana (01/01): ruta sensible.
A13: Holgura de la cadena de desarrollo (2.9), días hábiles | B13: =Tareas!K20 -> 40 | C13: Colchón que genera la restricción de balances.
A15: Costo base ascendente (USD) | B15: =Presupuesto!B18 -> 372700
A16: Costo base descendente N1 (USD) | B16: =CostoBaseN1 -> 398000
A17: Diferencia ascendente − descendente | B17: =Presupuesto!G12 -> -0.063567839 | C17: Se informa tal cual: la ascendente no se ajusta a la descendente.
A18: Línea base de costos (USD) | B18: =Presupuesto!B20 -> 394700 | C18: Costo base ascendente + contingencia.
A19: Reserva de gestión (USD) | B19: =Presupuesto!B21 -> 15788
A20: Presupuesto del proyecto (USD) | B20: =Presupuesto!B22 -> 410488
A21: Presupuesto autorizado en el Acta (USD) | B21: =Autorizado -> 420000
A22: Control: carga de recursos | B22: =IF(COUNTIF('Carga de recursos'!C148:N148,"SOBRECARGA")=0,"OK","REVISAR") -> OK | C22: Ningún recurso supera su capacidad.
A23: Control: costos | B23: =IF(AND(Presupuesto!C81="OK",Presupuesto!C82="OK"),"OK","REVISAR") -> OK | C23: Distribución mensual y suma por tarea.
A25: Hitos del Acta frente al plan
A26: Hito | B26: Descripción | C26: Tarea(s) que lo determinan | D26: Fecha del Acta | E26: Fecha del plan | F26: Margen (días corridos) | G26: Estado
A27: H-0 | B27: Kick-off y firma del Acta | C27: 1.1 (inicio) | D27: 46296 | E27: =Tareas!M6 -> 46296 | F27: =D27-E27 -> 0 | G27: =IF(E27<=D27,"Cumple","Desvío") -> Cumple
A28: H-1 | B28: Alcance y EDT ratificados; línea base confirmada | C28: 1.2 y 1.3 | D28: 46312 | E28: =MAX(Tareas!N7,Tareas!N8) -> 46308 | F28: =D28-E28 -> 4 | G28: =IF(E28<=D28,"Cumple","Desvío") -> Cumple
A29: H-2 | B29: Diseño UX/UI y reglas validados; inventario cargado | C29: 2.1, 2.2 y 2.7 | D29: 46347 | E29: =MAX(Tareas!N12,Tareas!N13,Tareas!N18) -> 46343 | F29: =D29-E29 -> 4 | G29: =IF(E29<=D29,"Cumple","Desvío") -> Cumple
A30: H-3 | B30: Piloto de la planta 3 completado | C30: 5.2 | D30: 46375 | E30: =Tareas!N32 -> 46374 | F30: =D30-E30 -> 1 | G30: =IF(E30<=D30,"Cumple","Desvío") -> Cumple
A31: H-4 | B31: Notificaciones completas; pruebas de seguridad, integración y carga | C31: 2.6, 3.4 y 3.5 | D31: 46445 | E31: =MAX(Tareas!N17,Tareas!N24,Tareas!N25) -> 46394 | F31: =D31-E31 -> 51 | G31: =IF(E31<=D31,"Cumple","Desvío") -> Cumple
A32: H-5 | B32: UAT ≥ 9,0/10 y acta de aceptación | C32: 5.3 | D32: 46466 | E32: =Tareas!N34 -> 46465 | F32: =D32-E32 -> 1 | G32: =IF(E32<=D32,"Cumple","Desvío") -> Cumple
A33: H-6 | B33: Puesta en producción en las cuatro plantas | C33: 5.4 (inicio) | D33: 46477 | E33: =Tareas!M35 -> 46477 | F33: =D33-E33 -> 0 | G33: =IF(E33<=D33,"Cumple","Desvío") -> Cumple
A34: H-7 | B34: Cierre, estabilización, tablero e informe entregados | C34: 5.4, 5.5, 5.6 y 1.6 | D34: 46507 | E34: =MAX(Tareas!N35,Tareas!N36,Tareas!N37,Tareas!N11) -> 46507 | F34: =D34-E34 -> 0 | G34: =IF(E34<=D34,"Cumple","Desvío") -> Cumple
A36: Varios hitos del Acta (H-1, H-2, H-3, H-5) caen en sábado; el plan los cumple con el último día hábil anterior.

Sheet Tareas
A1: WKH-2026 · Listado de tareas, red de actividades (CPM) y diagrama de Gantt
A2: Duraciones en días hábiles. ES/EF/LS/LF en días hábiles desde H-0 (EF = ES + duración). Las fechas salen de la hoja Calendario. R-3 representa la ventana de balances dentro de la red; la tarea 1.5 es un esfuerzo continuo (LOE) hasta el cierre y no determina el camino crítico.
A3: Fin de la red (días hábiles) | D3: =MAX(H6,H7,H8,H9,H11,H12,H13,H14,H15,H16,H17,H18,H19,H20,H21,H22,H23,H24,H25,H26,H27,H28,H29,H30,H31,H32,H33,H34,H35,H36,H37) -> 140 | O3: Semana (lunes)
O4: =InicioProyecto-WEEKDAY(InicioProyecto,2)+1 -> 46293 | P4: =O4+7 -> 46300 | Q4: =P4+7 -> 46307 | R4: =Q4+7 -> 46314 | S4: =R4+7 -> 46321 | T4: =S4+7 -> 46328 | U4: =T4+7 -> 46335 | V4: =U4+7 -> 46342 | W4: =V4+7 -> 46349 | ... AT4: =AS4+7 -> 46510
A5: ID | B5: Tarea | C5: Responsable | D5: Dur. (d háb.) | E5: Predecesoras | F5: Inicio no antes de | G5: ES | H5: EF | I5: LS | J5: LF | K5: Holgura | L5: Crítica | M5: Inicio | N5: Fin
A6: 1.1 | B6: Acta de constitución | C6: PM | D6: 2 | E6: — | G6: =MAX(0) -> 0 | H6: =G6+D6 -> 2 | I6: =J6-D6 -> 8 | J6: =MIN(I7-0,I8-0,I9-0) -> 10 | K6: =I6-G6 -> 8 | L6: =IF(K6=0,"Sí","") | M6: =INDEX(Calendario!$B$3:$B$172,G6+1) -> 46296 | N6: =INDEX(Calendario!$B$3:$B$172,H6) -> 46297
A7: 1.2 | B7: Declaración del alcance y EDT | C7: PM | D7: 6 | E7: 1.1 | G7: =MAX(0,H6+0) -> 2 | H7: =G7+D7 -> 8 | I7: =J7-D7 -> 10 | J7: =MIN(I12-0,I21-0) -> 16 | K7: =I7-G7 -> 8 | L7: =IF(K7=0,"Sí","") | M7: =INDEX(Calendario!$B$3:$B$172,G7+1) -> 46300 | N7: =INDEX(Calendario!$B$3:$B$172,H7) -> 46308
A8: 1.3 | B8: Cronograma, presupuesto y línea base | C8: PM | D8: 6 | E8: 1.1 | G8: =MAX(0,H6+0) -> 2 | H8: =G8+D8 -> 8 | I8: =J8-D8 -> 23 | J8: =I31-0 -> 29 | K8: =I8-G8 -> 21 | L8: =IF(K8=0,"Sí","") | M8: =INDEX(Calendario!$B$3:$B$172,G8+1) -> 46300 | N8: =INDEX(Calendario!$B$3:$B$172,H8) -> 46308
A9: 1.4 | B9: Registro de riesgos e interesados | C9: PM | D9: 5 | E9: 1.1 | G9: =MAX(0,H6+0) -> 2 | H9: =G9+D9 -> 7 | I9: =J9-D9 -> 16 | J9: =I26-0 -> 21 | K9: =I9-G9 -> 14 | L9: =IF(K9=0,"Sí","") | M9: =INDEX(Calendario!$B$3:$B$172,G9+1) -> 46300 | N9: =INDEX(Calendario!$B$3:$B$172,H9) -> 46304
A10: 1.5 | B10: Seguimiento, cambios e informes (tarea resumen) | C10: PM | D10: =H10-G10 -> 132 | E10: 1.2, 1.3, 1.4 (hasta el cierre) | G10: =MAX(H7,H8,H9) -> 8 | H10: =FinRed -> 140 | I10: =G10 -> 8 | J10: =H10 -> 140 | K10: =I10-G10 -> 0 | L10: LOE | M10: =INDEX(Calendario!$B$3:$B$172,G10+1) -> 46309 | N10: =INDEX(Calendario!$B$3:$B$172,H10) -> 46507
A11: 1.6 | B11: Cierre y lecciones aprendidas | C11: PM | D11: 5 | E11: 5.5 (FF+0), 5.6 (FF+0) | G11: =MAX(0,H36+0-D11,H37+0-D11) -> 135 | H11: =G11+D11 -> 140 | I11: =J11-D11 -> 135 | J11: =FinRed -> 140 | K11: =I11-G11 -> 0 | L11: =IF(K11=0,"Sí","") -> Sí | M11: =INDEX(Calendario!$B$3:$B$172,G11+1) -> 46503 | N11: =INDEX(Calendario!$B$3:$B$172,H11) -> 46507
A12: 2.1 | B12: Relevamiento y reglas de negocio | C12: PO | D12: 10 | E12: 1.2 | G12: =MAX(0,H7+0) -> 8 | H12: =G12+D12 -> 18 | I12: =J12-D12 -> 16 | J12: =MIN(I13-0,I14-SS_23+D12,I15-0,I18-0) -> 26 | K12: =I12-G12 -> 8 | L12: =IF(K12=0,"Sí","") | M12: =INDEX(Calendario!$B$3:$B$172,G12+1) -> 46309 | N12: =INDEX(Calendario!$B$3:$B$172,H12) -> 46322
A13: 2.2 | B13: Planos e inventario de espacios | C13: SG VCA | D13: 15 | E13: 2.1 | G13: =MAX(0,H12+0) -> 18 | H13: =G13+D13 -> 33 | I13: =J13-D13 -> 26 | J13: =I32-0 -> 41 | K13: =I13-G13 -> 8 | L13: =IF(K13=0,"Sí","") | M13: =INDEX(Calendario!$B$3:$B$172,G13+1) -> 46323 | N13: =INDEX(Calendario!$B$3:$B$172,H13) -> 46343
A14: 2.3 | B14: Módulo de reserva de escritorios | C14: Desarrollo | D14: 18 | E14: 2.1 (SS+5) | G14: =MAX(0,G12+SS_23) -> 13 | H14: =G14+D14 -> 31 | I14: =J14-D14 -> 23 | J14: =MIN(I16-0,I32-0) -> 41 | K14: =I14-G14 -> 10 | L14: =IF(K14=0,"Sí","") | M14: =INDEX(Calendario!$B$3:$B$172,G14+1) -> 46316 | N14: =INDEX(Calendario!$B$3:$B$172,H14) -> 46339
A15: 2.4 | B15: Módulo de reserva de salas | C15: Desarrollo | D15: 15 | E15: 2.1 | G15: =MAX(0,H12+0) -> 18 | H15: =G15+D15 -> 33 | I15: =J15-D15 -> 26 | J15: =I32-0 -> 41 | K15: =I15-G15 -> 8 | L15: =IF(K15=0,"Sí","") | M15: =INDEX(Calendario!$B$3:$B$172,G15+1) -> 46323 | N15: =INDEX(Calendario!$B$3:$B$172,H15) -> 46343
A16: 2.5 | B16: Check-in, check-out y liberación | C16: Desarrollo | D16: 12 | E16: 2.3 | G16: =MAX(0,H14+0) -> 31 | H16: =G16+D16 -> 43 | I16: =J16-D16 -> 71 | J16: =I17-0 -> 83 | K16: =I16-G16 -> 40 | L16: =IF(K16=0,"Sí","") | M16: =INDEX(Calendario!$B$3:$B$172,G16+1) -> 46342 | N16: =INDEX(Calendario!$B$3:$B$172,H16) -> 46358
A17: 2.6 | B17: Notificaciones y sugerencias | C17: Desarrollo | D17: 15 | E17: 2.5, 3.2 | G17: =MAX(0,H16+0,H22+0) -> 43 | H17: =G17+D17 -> 58 | I17: =J17-D17 -> 83 | J17: =MIN(I20-0,I25-SS_35+D17) -> 98 | K17: =I17-G17 -> 40 | L17: =IF(K17=0,"Sí","") | M17: =INDEX(Calendario!$B$3:$B$172,G17+1) -> 46359 | N17: =INDEX(Calendario!$B$3:$B$172,H17) -> 46384
A18: 2.7 | B18: Diseño UX | C18: UX/UI | D18: 15 | E18: 2.1 | G18: =MAX(0,H12+0) -> 18 | H18: =G18+D18 -> 33 | I18: =J18-D18 -> 26 | J18: =MIN(I19-0,I20-0,I32-0) -> 41 | K18: =I18-G18 -> 8 | L18: =IF(K18=0,"Sí","") | M18: =INDEX(Calendario!$B$3:$B$172,G18+1) -> 46323 | N18: =INDEX(Calendario!$B$3:$B$172,H18) -> 46343
A19: 2.8 | B19: Implementación bot de Teams | C19: Desarrollo | D19: 10 | E19: 2.7, 3.3 | G19: =MAX(0,H18+0,H23+0) -> 33 | H19: =G19+D19 -> 43 | I19: =J19-D19 -> 100 | J19: =I34-0 -> 110 | K19: =I19-G19 -> 67 | L19: =IF(K19=0,"Sí","") | M19: =INDEX(Calendario!$B$3:$B$172,G19+1) -> 46344 | N19: =INDEX(Calendario!$B$3:$B$172,H19) -> 46358
A20: 2.9 | B20: Configuración web | C20: Desarrollo | D20: 12 | E20: 2.6, 2.7 | G20: =MAX(0,H17+0,H18+0) -> 58 | H20: =G20+D20 -> 70 | I20: =J20-D20 -> 98 | J20: =I34-0 -> 110 | K20: =I20-G20 -> 40 | L20: =IF(K20=0,"Sí","") | M20: =INDEX(Calendario!$B$3:$B$172,G20+1) -> 46385 | N20: =INDEX(Calendario!$B$3:$B$172,H20) -> 46401
A21: 3.1 | B21: SSO y SCIM con Entra ID | C21: Integraciones + Tec. VCA | D21: 12 | E21: 1.2 | G21: =MAX(0,H7+0) -> 8 | H21: =G21+D21 -> 20 | I21: =J21-D21 -> 29 | J21: =MIN(I22-0,I23-0,I32-0) -> 41 | K21: =I21-G21 -> 21 | L21: =IF(K21=0,"Sí","") | M21: =INDEX(Calendario!$B$3:$B$172,G21+1) -> 46309 | N21: =INDEX(Calendario!$B$3:$B$172,H21) -> 46324
A22: 3.2 | B22: Sincronización con HRIS | C22: Integraciones + Tec. VCA | D22: 10 | E22: 3.1 | G22: =MAX(0,H21+0) -> 20 | H22: =G22+D22 -> 30 | I22: =J22-D22 -> 73 | J22: =MIN(I17-0,I24-0) -> 83 | K22: =I22-G22 -> 53 | L22: =IF(K22=0,"Sí","") | M22: =INDEX(Calendario!$B$3:$B$172,G22+1) -> 46325 | N22: =INDEX(Calendario!$B$3:$B$172,H22) -> 46338
A23: 3.3 | B23: Exchange, Outlook y Teams | C23: Integraciones + Tec. VCA | D23: 10 | E23: 3.1 | G23: =MAX(0,H21+0) -> 20 | H23: =G23+D23 -> 30 | I23: =J23-D23 -> 73 | J23: =MIN(I19-0,I24-0) -> 83 | K23: =I23-G23 -> 53 | L23: =IF(K23=0,"Sí","") | M23: =INDEX(Calendario!$B$3:$B$172,G23+1) -> 46325 | N23: =INDEX(Calendario!$B$3:$B$172,H23) -> 46338
A24: 3.4 | B24: Seguridad y endurecimiento | C24: QA | D24: 15 | E24: 3.2, 3.3 | G24: =MAX(0,H22+0,H23+0) -> 30 | H24: =G24+D24 -> 45 | I24: =J24-D24 -> 83 | J24: =I25-0 -> 98 | K24: =I24-G24 -> 53 | L24: =IF(K24=0,"Sí","") | M24: =INDEX(Calendario!$B$3:$B$172,G24+1) -> 46339 | N24: =INDEX(Calendario!$B$3:$B$172,H24) -> 46360
A25: 3.5 | B25: Pruebas de integración y carga | C25: QA | D25: 12 | E25: 3.4, 2.6 (SS+10) | G25: =MAX(0,H24+0,G17+SS_35) -> 53 | H25: =G25+D25 -> 65 | I25: =J25-D25 -> 98 | J25: =I34-0 -> 110 | K25: =I25-G25 -> 45 | L25: =IF(K25=0,"Sí","") | M25: =INDEX(Calendario!$B$3:$B$172,G25+1) -> 46377 | N25: =INDEX(Calendario!$B$3:$B$172,H25) -> 46394
A26: 4.1 | B26: Impacto e interesados con RR.HH. | C26: Gest. del cambio + RR.HH. | D26: 10 | E26: 1.4 | G26: =MAX(0,H9+0) -> 7 | H26: =G26+D26 -> 17 | I26: =J26-D26 -> 21 | J26: =I27-0 -> 31 | K26: =I26-G26 -> 14 | L26: =IF(K26=0,"Sí","") | M26: =INDEX(Calendario!$B$3:$B$172,G26+1) -> 46308 | N26: =INDEX(Calendario!$B$3:$B$172,H26) -> 46321
A27: 4.2 | B27: Política de trabajo flexible | C27: Gest. del cambio + RR.HH. | D27: 10 | E27: 4.1 | G27: =MAX(0,H26+0) -> 17 | H27: =G27+D27 -> 27 | I27: =J27-D27 -> 31 | J27: =MIN(I28-0,I29-0,I32-0) -> 41 | K27: =I27-G27 -> 14 | L27: =IF(K27=0,"Sí","") | M27: =INDEX(Calendario!$B$3:$B$172,G27+1) -> 46322 | N27: =INDEX(Calendario!$B$3:$B$172,H27) -> 46335
A28: 4.3 | B28: Comunicación y lanzamiento | C28: Gest. del cambio + RR.HH. | D28: 15 | E28: 4.2 | F28: 46447 | G28: =MAX(0,NETWORKDAYS(InicioProyecto,F28-1,Feriados),H27+0) -> 99 | H28: =G28+D28 -> 114 | I28: =J28-D28 -> 103 | J28: =I35-0 -> 118 | K28: =I28-G28 -> 4 | L28: =IF(K28=0,"Sí","") | M28: =INDEX(Calendario!$B$3:$B$172,G28+1) -> 46447 | N28: =INDEX(Calendario!$B$3:$B$172,H28) -> 46465
A29: 4.4 | B29: Referentes y capacitación | C29: Gest. del cambio + RR.HH. | D29: 15 | E29: 4.2 | G29: =MAX(0,H27+0) -> 27 | H29: =G29+D29 -> 42 | I29: =J29-D29 -> 85 | J29: =I30-0 -> 100 | K29: =I29-G29 -> 58 | L29: =IF(K29=0,"Sí","") | M29: =INDEX(Calendario!$B$3:$B$172,G29+1) -> 46336 | N29: =INDEX(Calendario!$B$3:$B$172,H29) -> 46357
A30: 4.5 | B30: Materiales y mesa de ayuda N1 | C30: Gest. del cambio + RR.HH. | D30: 10 | E30: 4.4 | G30: =MAX(0,H29+0) -> 42 | H30: =G30+D30 -> 52 | I30: =J30-D30 -> 100 | J30: =I34-0 -> 110 | K30: =I30-G30 -> 58 | L30: =IF(K30=0,"Sí","") | M30: =INDEX(Calendario!$B$3:$B$172,G30+1) -> 46358 | N30: =INDEX(Calendario!$B$3:$B$172,H30) -> 46373
A31: 5.1 | B31: Ambientes, migración y despliegue | C31: DevOps | D31: 12 | E31: 1.3 | G31: =MAX(0,H8+0) -> 8 | H31: =G31+D31 -> 20 | I31: =J31-D31 -> 29 | J31: =I32-0 -> 41 | K31: =I31-G31 -> 21 | L31: =IF(K31=0,"Sí","") | M31: =INDEX(Calendario!$B$3:$B$172,G31+1) -> 46309 | N31: =INDEX(Calendario!$B$3:$B$172,H31) -> 46324
A32: 5.2 | B32: Piloto y ajustes | C32: PO | D32: 20 | E32: 2.2, 2.3, 2.4, 2.7, 3.1, 4.2, 5.1 | G32: =MAX(0,H13+0,H14+0,H15+0,H18+0,H21+0,H27+0,H31+0) -> 33 | H32: =G32+D32 -> 53 | I32: =J32-D32 -> 41 | J32: =I33-0 -> 61 | K32: =I32-G32 -> 8 | L32: =IF(K32=0,"Sí","") | M32: =INDEX(Calendario!$B$3:$B$172,G32+1) -> 46344 | N32: =INDEX(Calendario!$B$3:$B$172,H32) -> 46374
A33: R-3 | B33: Ventana de balances de VCA (restricción R-3 de la N1) | C33: VCA (restricción externa) | D33: =NETWORKDAYS(VentanaDesde,VentanaHasta,Feriados) -> 49 | E33: 5.2 | F33: =VentanaDesde -> 46388 | G33: =MAX(0,NETWORKDAYS(InicioProyecto,F33-1,Feriados),H32+0) -> 61 | H33: =G33+D33 -> 110 | I33: =J33-D33 -> 61 | J33: =I34-0 -> 110 | K33: =I33-G33 -> 0 | L33: =IF(K33=0,"Sí","") -> Sí | M33: =INDEX(Calendario!$B$3:$B$172,G33+1) -> 46391 | N33: =INDEX(Calendario!$B$3:$B$172,H33) -> 46461
A34: 5.3 | B34: UAT y acta de aceptación | C34: QA + PO | D34: 4 | E34: R-3, 2.8, 2.9, 3.5, 4.5 | G34: =MAX(0,H33+0,H19+0,H20+0,H25+0,H30+0) -> 110 | H34: =G34+D34 -> 114 | I34: =J34-D34 -> 110 | J34: =I35-LAG_54 -> 114 | K34: =I34-G34 -> 0 | L34: =IF(K34=0,"Sí","") -> Sí | M34: =INDEX(Calendario!$B$3:$B$172,G34+1) -> 46462 | N34: =INDEX(Calendario!$B$3:$B$172,H34) -> 46465
A35: 5.4 | B35: Go-live y estabilización (4 semanas) | C35: PM + equipo | D35: 20 | E35: 5.3 (FS+4), 4.3 | G35: =MAX(0,H34+LAG_54,H28+0) -> 118 | H35: =G35+D35 -> 138 | I35: =J35-D35 -> 118 | J35: =MIN(J36-FF_5x,J37-FF_5x) -> 138 | K35: =I35-G35 -> 0 | L35: =IF(K35=0,"Sí","") -> Sí | M35: =INDEX(Calendario!$B$3:$B$172,G35+1) -> 46477 | N35: =INDEX(Calendario!$B$3:$B$172,H35) -> 46505
A36: 5.5 | B36: Tablero y transferencia del seguimiento | C36: PO + VCA | D36: 10 | E36: 5.4 (FF+2) | G36: =MAX(0,H35+FF_5x-D36) -> 130 | H36: =G36+D36 -> 140 | I36: =J36-D36 -> 130 | J36: =J11-0 -> 140 | K36: =I36-G36 -> 0 | L36: =IF(K36=0,"Sí","") -> Sí | M36: =INDEX(Calendario!$B$3:$B$172,G36+1) -> 46496 | N36: =INDEX(Calendario!$B$3:$B$172,H36) -> 46507
A37: 5.6 | B37: Informe de ocupación y recomendación | C37: Serv. Generales VCA | D37: 10 | E37: 5.4 (FF+2) | G37: =MAX(0,H35+FF_5x-D37) -> 130 | H37: =G37+D37 -> 140 | I37: =J37-D37 -> 130 | J37: =J11-0 -> 140 | K37: =I37-G37 -> 0 | L37: =IF(K37=0,"Sí","") -> Sí | M37: =INDEX(Calendario!$B$3:$B$172,G37+1) -> 46496 | N37: =INDEX(Calendario!$B$3:$B$172,H37) -> 46507
A39: Leyenda
B40: Camino crítico (holgura 0)
B41: Tarea con holgura
B42: Ventana de balances (R-3)
B43: Tarea resumen (LOE)
B45: Nota: la duración de 1.5 se calcula como (fin de la red − su inicio) y es la misma en el listado, en el Gantt y en el diagrama AON. La holgura de las tareas previas a R-3 se mide contra el inicio de la ventana (01/01): el piloto no puede deslizar hacia dentro de la ventana.

Sheet Costos
A1: Base de cálculo del costo de cada tarea: recurso × tarifa × días
A2: Costo = unidades (FTE) × duración de la tarea × tarifa diaria. La duración se toma de la hoja Tareas; la tarifa, de la hoja Recursos. Ninguna cifra se ajusta para igualar un total.
A4: Tarea | B4: Descripción | C4: Rol | D4: Recurso | E4: Unidades (FTE) | F4: Duración (d háb.) | G4: Días-persona | H4: Tarifa USD/día | I4: Costo USD | J4: Línea de costo (N1) | K4: ES | L4: EF
A5: 1.1 | B5: =INDEX(Tareas!$B$6:$B$37,MATCH($A5,Tareas!$A$6:$A$37,0)) -> Acta de constitución | C5: PM | D5: =INDEX(Recursos!$B$5:$B$16,MATCH($C5,Recursos!$A$5:$A$16,0)) -> Project Manager (Tandem) | E5: 1 | F5: =INDEX(Tareas!$D$6:$D$37,MATCH($A5,Tareas!$A$6:$A$37,0)) -> 2 | G5: =E5*F5 -> 2 | H5: =INDEX(Recursos!$D$5:$D$16,MATCH($C5,Recursos!$A$5:$A$16,0)) -> 520 | I5: =G5*H5 -> 1040 | J5: =INDEX(Recursos!$C$5:$C$16,MATCH($C5,Recursos!$A$5:$A$16,0)) -> Equipo Tandem | K5: =INDEX(Tareas!$G$6:$G$37,MATCH($A5,Tareas!$A$6:$A$37,0)) -> 0 | L5: =INDEX(Tareas!$H$6:$H$37,MATCH($A5,Tareas!$A$6:$A$37,0)) -> 2
A6: 1.2 | B6: =INDEX(Tareas!$B$6:$B$37,MATCH($A6,Tareas!$A$6:$A$37,0)) -> Declaración del alcance y EDT | C6: PM | D6: =INDEX(Recursos!$B$5:$B$16,MATCH($C6,Recursos!$A$5:$A$16,0)) -> Project Manager (Tandem) | E6: 0.5 | F6: =INDEX(Tareas!$D$6:$D$37,MATCH($A6,Tareas!$A$6:$A$37,0)) -> 6 | G6: =E6*F6 -> 3 | H6: =INDEX(Recursos!$D$5:$D$16,MATCH($C6,Recursos!$A$5:$A$16,0)) -> 520 | I6: =G6*H6 -> 1560 | J6: =INDEX(Recursos!$C$5:$C$16,MATCH($C6,Recursos!$A$5:$A$16,0)) -> Equipo Tandem | K6: =INDEX(Tareas!$G$6:$G$37,MATCH($A6,Tareas!$A$6:$A$37,0)) -> 2 | L6: =INDEX(Tareas!$H$6:$H$37,MATCH($A6,Tareas!$A$6:$A$37,0)) -> 8
A7: 1.2 | B7: =INDEX(Tareas!$B$6:$B$37,MATCH($A7,Tareas!$A$6:$A$37,0)) -> Declaración del alcance y EDT | C7: PO | D7: =INDEX(Recursos!$B$5:$B$16,MATCH($C7,Recursos!$A$5:$A$16,0)) -> Product Owner (Tandem) | E7: 0.2 | F7: =INDEX(Tareas!$D$6:$D$37,MATCH($A7,Tareas!$A$6:$A$37,0)) -> 6 | G7: =E7*F7 -> 1.2 | H7: =INDEX(Recursos!$D$5:$D$16,MATCH($C7,Recursos!$A$5:$A$16,0)) -> 480 | I7: =G7*H7 -> 576 | J7: =INDEX(Recursos!$C$5:$C$16,MATCH($C7,Recursos!$A$5:$A$16,0)) -> Equipo Tandem | K7: =INDEX(Tareas!$G$6:$G$37,MATCH($A7,Tareas!$A$6:$A$37,0)) -> 2 | L7: =INDEX(Tareas!$H$6:$H$37,MATCH($A7,Tareas!$A$6:$A$37,0)) -> 8
A8: 1.3 | B8: =INDEX(Tareas!$B$6:$B$37,MATCH($A8,Tareas!$A$6:$A$37,0)) -> Cronograma, presupuesto y línea base | C8: PM | D8: =INDEX(Recursos!$B$5:$B$16,MATCH($C8,Recursos!$A$5:$A$16,0)) -> Project Manager (Tandem) | E8: 0.3 | F8: =INDEX(Tareas!$D$6:$D$37,MATCH($A8,Tareas!$A$6:$A$37,0)) -> 6 | G8: =E8*F8 -> 1.8 | H8: =INDEX(Recursos!$D$5:$D$16,MATCH($C8,Recursos!$A$5:$A$16,0)) -> 520 | I8: =G8*H8 -> 936 | J8: =INDEX(Recursos!$C$5:$C$16,MATCH($C8,Recursos!$A$5:$A$16,0)) -> Equipo Tandem | K8: =INDEX(Tareas!$G$6:$G$37,MATCH($A8,Tareas!$A$6:$A$37,0)) -> 2 | L8: =INDEX(Tareas!$H$6:$H$37,MATCH($A8,Tareas!$A$6:$A$37,0)) -> 8
A9: 1.4 | B9: =INDEX(Tareas!$B$6:$B$37,MATCH($A9,Tareas!$A$6:$A$37,0)) -> Registro de riesgos e interesados | C9: PM | D9: =INDEX(Recursos!$B$5:$B$16,MATCH($C9,Recursos!$A$5:$A$16,0)) -> Project Manager (Tandem) | E9: 0.2 | F9: =INDEX(Tareas!$D$6:$D$37,MATCH($A9,Tareas!$A$6:$A$37,0)) -> 5 | G9: =E9*F9 -> 1 | H9: =INDEX(Recursos!$D$5:$D$16,MATCH($C9,Recursos!$A$5:$A$16,0)) -> 520 | I9: =G9*H9 -> 520 | J9: =INDEX(Recursos!$C$5:$C$16,MATCH($C9,Recursos!$A$5:$A$16,0)) -> Equipo Tandem | K9: =INDEX(Tareas!$G$6:$G$37,MATCH($A9,Tareas!$A$6:$A$37,0)) -> 2 | L9: =INDEX(Tareas!$H$6:$H$37,MATCH($A9,Tareas!$A$6:$A$37,0)) -> 7
A10: 1.4 | B10: =INDEX(Tareas!$B$6:$B$37,MATCH($A10,Tareas!$A$6:$A$37,0)) -> Registro de riesgos e interesados | C10: RH | D10: =INDEX(Recursos!$B$5:$B$16,MATCH($C10,Recursos!$A$5:$A$16,0)) -> RR.HH. VCA (S. Ibarra / referente) | E10: 0.1 | F10: =INDEX(Tareas!$D$6:$D$37,MATCH($A10,Tareas!$A$6:$A$37,0)) -> 5 | G10: =E10*F10 -> 0.5 | H10: =INDEX(Recursos!$D$5:$D$16,MATCH($C10,Recursos!$A$5:$A$16,0)) -> 160 | I10: =G10*H10 -> 80 | J10: =INDEX(Recursos!$C$5:$C$16,MATCH($C10,Recursos!$A$5:$A$16,0)) -> Horas VCA | K10: =INDEX(Tareas!$G$6:$G$37,MATCH($A10,Tareas!$A$6:$A$37,0)) -> 2 | L10: =INDEX(Tareas!$H$6:$H$37,MATCH($A10,Tareas!$A$6:$A$37,0)) -> 7
A11: 1.5 | B11: =INDEX(Tareas!$B$6:$B$37,MATCH($A11,Tareas!$A$6:$A$37,0)) -> Seguimiento, cambios e informes (tarea resumen) | C11: PM | D11: =INDEX(Recursos!$B$5:$B$16,MATCH($C11,Recursos!$A$5:$A$16,0)) -> Project Manager (Tandem) | E11: 0.5 | F11: =INDEX(Tareas!$D$6:$D$37,MATCH($A11,Tareas!$A$6:$A$37,0)) -> 132 | G11: =E11*F11 -> 66 | H11: =INDEX(Recursos!$D$5:$D$16,MATCH($C11,Recursos!$A$5:$A$16,0)) -> 520 | I11: =G11*H11 -> 34320 | J11: =INDEX(Recursos!$C$5:$C$16,MATCH($C11,Recursos!$A$5:$A$16,0)) -> Equipo Tandem | K11: =INDEX(Tareas!$G$6:$G$37,MATCH($A11,Tareas!$A$6:$A$37,0)) -> 8 | L11: =INDEX(Tareas!$H$6:$H$37,MATCH($A11,Tareas!$A$6:$A$37,0)) -> 140
A12: 1.6 | B12: =INDEX(Tareas!$B$6:$B$37,MATCH($A12,Tareas!$A$6:$A$37,0)) -> Cierre y lecciones aprendidas | C12: PM | D12: =INDEX(Recursos!$B$5:$B$16,MATCH($C12,Recursos!$A$5:$A$16,0)) -> Project Manager (Tandem) | E12: 0.3 | F12: =INDEX(Tareas!$D$6:$D$37,MATCH($A12,Tareas!$A$6:$A$37,0)) -> 5 | G12: =E12*F12 -> 1.5 | H12: =INDEX(Recursos!$D$5:$D$16,MATCH($C12,Recursos!$A$5:$A$16,0)) -> 520 | I12: =G12*H12 -> 780 | J12: =INDEX(Recursos!$C$5:$C$16,MATCH($C12,Recursos!$A$5:$A$16,0)) -> Equipo Tandem | K12: =INDEX(Tareas!$G$6:$G$37,MATCH($A12,Tareas!$A$6:$A$37,0)) -> 135 | L12: =INDEX(Tareas!$H$6:$H$37,MATCH($A12,Tareas!$A$6:$A$37,0)) -> 140
A13: 1.6 | B13: =INDEX(Tareas!$B$6:$B$37,MATCH($A13,Tareas!$A$6:$A$37,0)) -> Cierre y lecciones aprendidas | C13: PO | D13: =INDEX(Recursos!$B$5:$B$16,MATCH($C13,Recursos!$A$5:$A$16,0)) -> Product Owner (Tandem) | E13: 0.1 | F13: =INDEX(Tareas!$D$6:$D$37,MATCH($A13,Tareas!$A$6:$A$37,0)) -> 5 | G13: =E13*F13 -> 0.5 | H13: =INDEX(Recursos!$D$5:$D$16,MATCH($C13,Recursos!$A$5:$A$16,0)) -> 480 | I13: =G13*H13 -> 240 | J13: =INDEX(Recursos!$C$5:$C$16,MATCH($C13,Recursos!$A$5:$A$16,0)) -> Equipo Tandem | K13: =INDEX(Tareas!$G$6:$G$37,MATCH($A13,Tareas!$A$6:$A$37,0)) -> 135 | L13: =INDEX(Tareas!$H$6:$H$37,MATCH($A13,Tareas!$A$6:$A$37,0)) -> 140
A14: 2.1 | B14: =INDEX(Tareas!$B$6:$B$37,MATCH($A14,Tareas!$A$6:$A$37,0)) -> Relevamiento y reglas de negocio | C14: PO | D14: =INDEX(Recursos!$B$5:$B$16,MATCH($C14,Recursos!$A$5:$A$16,0)) -> Product Owner (Tandem) | E14: 1 | F14: =INDEX(Tareas!$D$6:$D$37,MATCH($A14,Tareas!$A$6:$A$37,0)) -> 10 | G14: =E14*F14 -> 10 | H14: =INDEX(Recursos!$D$5:$D$16,MATCH($C14,Recursos!$A$5:$A$16,0)) -> 480 | I14: =G14*H14 -> 4800 | J14: =INDEX(Recursos!$C$5:$C$16,MATCH($C14,Recursos!$A$5:$A$16,0)) -> Equipo Tandem | K14: =INDEX(Tareas!$G$6:$G$37,MATCH($A14,Tareas!$A$6:$A$37,0)) -> 8 | L14: =INDEX(Tareas!$H$6:$H$37,MATCH($A14,Tareas!$A$6:$A$37,0)) -> 18
A15: 2.1 | B15: =INDEX(Tareas!$B$6:$B$37,MATCH($A15,Tareas!$A$6:$A$37,0)) -> Relevamiento y reglas de negocio | C15: PM | D15: =INDEX(Recursos!$B$5:$B$16,MATCH($C15,Recursos!$A$5:$A$16,0)) -> Project Manager (Tandem) | E15: 0.2 | F15: =INDEX(Tareas!$D$6:$D$37,MATCH($A15,Tareas!$A$6:$A$37,0)) -> 10 | G15: =E15*F15 -> 2 | H15: =INDEX(Recursos!$D$5:$D$16,MATCH($C15,Recursos!$A$5:$A$16,0)) -> 520 | I15: =G15*H15 -> 1040 | J15: =INDEX(Recursos!$C$5:$C$16,MATCH($C15,Recursos!$A$5:$A$16,0)) -> Equipo Tandem | K15: =INDEX(Tareas!$G$6:$G$37,MATCH($A15,Tareas!$A$6:$A$37,0)) -> 8 | L15: =INDEX(Tareas!$H$6:$H$37,MATCH($A15,Tareas!$A$6:$A$37,0)) -> 18
A16: 2.1 | B16: =INDEX(Tareas!$B$6:$B$37,MATCH($A16,Tareas!$A$6:$A$37,0)) -> Relevamiento y reglas de negocio | C16: SG | D16: =INDEX(Recursos!$B$5:$B$16,MATCH($C16,Recursos!$A$5:$A$16,0)) -> Servicios Generales VCA (D. Sosa) | E16: 0.2 | F16: =INDEX(Tareas!$D$6:$D$37,MATCH($A16,Tareas!$A$6:$A$37,0)) -> 10 | G16: =E16*F16 -> 2 | H16: =INDEX(Recursos!$D$5:$D$16,MATCH($C16,Recursos!$A$5:$A$16,0)) -> 170 | I16: =G16*H16 -> 340 | J16: =INDEX(Recursos!$C$5:$C$16,MATCH($C16,Recursos!$A$5:$A$16,0)) -> Horas VCA | K16: =INDEX(Tareas!$G$6:$G$37,MATCH($A16,Tareas!$A$6:$A$37,0)) -> 8 | L16: =INDEX(Tareas!$H$6:$H$37,MATCH($A16,Tareas!$A$6:$A$37,0)) -> 18
... A72: 5.3 | B72: =INDEX(Tareas!$B$6:$B$37,MATCH($A72,Tareas!$A$6:$A$37,0)) -> UAT y acta de aceptación | C72: TEC | D72: =INDEX(Recursos!$B$5:$B$16,MATCH($C72,Recursos!$A$5:$A$16,0)) -> Tecnología VCA (P. Guzmán) | E72: 0.3 | F72: =INDEX(Tareas!$D$6:$D$37,MATCH($A72,Tareas!$A$6:$A$37,0)) -> 4 | G72: =E72*F72 -> 1.2 | H72: =INDEX(Recursos!$D$5:$D$16,MATCH($C72,Recursos!$A$5:$A$16,0)) -> 190 | I72: =G72*H72 -> 228 | J72: =INDEX(Recursos!$C$5:$C$16,MATCH($C72,Recursos!$A$5:$A$16,0)) -> Horas VCA | K72: =INDEX(Tareas!$G$6:$G$37,MATCH($A72,Tareas!$A$6:$A$37,0)) -> 110 | L72: =INDEX(Tareas!$H$6:$H$37,MATCH($A72,Tareas!$A$6:$A$37,0)) -> 114
A73: 5.3 | B73: =INDEX(Tareas!$B$6:$B$37,MATCH($A73,Tareas!$A$6:$A$37,0)) -> UAT y acta de aceptación | C73: USR | D73: =INDEX(Recursos!$B$5:$B$16,MATCH($C73,Recursos!$A$5:$A$16,0)) -> Usuarios de prueba UAT (VCA) | E73: =(UsuariosUAT*HorasUAT/8)/F73 -> 5.625 | F73: =INDEX(Tareas!$D$6:$D$37,MATCH($A73,Tareas!$A$6:$A$37,0)) -> 4 | G73: =E73*F73 -> 22.5 | H73: =INDEX(Recursos!$D$5:$D$16,MATCH($C73,Recursos!$A$5:$A$16,0)) -> 150 | I73: =G73*H73 -> 3375 | J73: =INDEX(Recursos!$C$5:$C$16,MATCH($C73,Recursos!$A$5:$A$16,0)) -> Horas VCA | K73: =INDEX(Tareas!$G$6:$G$37,MATCH($A73,Tareas!$A$6:$A$37,0)) -> 110 | L73: =INDEX(Tareas!$H$6:$H$37,MATCH($A73,Tareas!$A$6:$A$37,0)) -> 114
A74: 5.4 | B74: =INDEX(Tareas!$B$6:$B$37,MATCH($A74,Tareas!$A$6:$A$37,0)) -> Go-live y estabilización (4 semanas) | C74: PM | D74: =INDEX(Recursos!$B$5:$B$16,MATCH($C74,Recursos!$A$5:$A$16,0)) -> Project Manager (Tandem) | E74: 0.2 | F74: =INDEX(Tareas!$D$6:$D$37,MATCH($A74,Tareas!$A$6:$A$37,0)) -> 20 | G74: =E74*F74 -> 4 | H74: =INDEX(Recursos!$D$5:$D$16,MATCH($C74,Recursos!$A$5:$A$16,0)) -> 520 | I74: =G74*H74 -> 2080 | J74: =INDEX(Recursos!$C$5:$C$16,MATCH($C74,Recursos!$A$5:$A$16,0)) -> Equipo Tandem | K74: =INDEX(Tareas!$G$6:$G$37,MATCH($A74,Tareas!$A$6:$A$37,0)) -> 118 | L74: =INDEX(Tareas!$H$6:$H$37,MATCH($A74,Tareas!$A$6:$A$37,0)) -> 138
A75: 5.4 | B75: =INDEX(Tareas!$B$6:$B$37,MATCH($A75,Tareas!$A$6:$A$37,0)) -> Go-live y estabilización (4 semanas) | C75: PO | D75: =INDEX(Recursos!$B$5:$B$16,MATCH($C75,Recursos!$A$5:$A$16,0)) -> Product Owner (Tandem) | E75: 0.3 | F75: =INDEX(Tareas!$D$6:$D$37,MATCH($A75,Tareas!$A$6:$A$37,0)) -> 20 | G75: =E75*F75 -> 6 | H75: =INDEX(Recursos!$D$5:$D$16,MATCH($C75,Recursos!$A$5:$A$16,0)) -> 480 | I75: =G75*H75 -> 2880 | J75: =INDEX(Recursos!$C$5:$C$16,MATCH($C75,Recursos!$A$5:$A$16,0)) -> Equipo Tandem | K75: =INDEX(Tareas!$G$6:$G$37,MATCH($A75,Tareas!$A$6:$A$37,0)) -> 118 | L75: =INDEX(Tareas!$H$6:$H$37,MATCH($A75,Tareas!$A$6:$A$37,0)) -> 138
A76: 5.4 | B76: =INDEX(Tareas!$B$6:$B$37,MATCH($A76,Tareas!$A$6:$A$37,0)) -> Go-live y estabilización (4 semanas) | C76: DEV | D76: =INDEX(Recursos!$B$5:$B$16,MATCH($C76,Recursos!$A$5:$A$16,0)) -> Desarrollador/a full-stack (Tandem) | E76: 1.5 | F76: =INDEX(Tareas!$D$6:$D$37,MATCH($A76,Tareas!$A$6:$A$37,0)) -> 20 | G76: =E76*F76 -> 30 | H76: =INDEX(Recursos!$D$5:$D$16,MATCH($C76,Recursos!$A$5:$A$16,0)) -> 440 | I76: =G76*H76 -> 13200 | J76: =INDEX(Recursos!$C$5:$C$16,MATCH($C76,Recursos!$A$5:$A$16,0)) -> Equipo Tandem | K76: =INDEX(Tareas!$G$6:$G$37,MATCH($A76,Tareas!$A$6:$A$37,0)) -> 118 | L76: =INDEX(Tareas!$H$6:$H$37,MATCH($A76,Tareas!$A$6:$A$37,0)) -> 138
A77: 5.4 | B77: =INDEX(Tareas!$B$6:$B$37,MATCH($A77,Tareas!$A$6:$A$37,0)) -> Go-live y estabilización (4 semanas) | C77: QA | D77: =INDEX(Recursos!$B$5:$B$16,MATCH($C77,Recursos!$A$5:$A$16,0)) -> Especialista QA (Tandem) | E77: 0.5 | F77: =INDEX(Tareas!$D$6:$D$37,MATCH($A77,Tareas!$A$6:$A$37,0)) -> 20 | G77: =E77*F77 -> 10 | H77: =INDEX(Recursos!$D$5:$D$16,MATCH($C77,Recursos!$A$5:$A$16,0)) -> 360 | I77: =G77*H77 -> 3600 | J77: =INDEX(Recursos!$C$5:$C$16,MATCH($C77,Recursos!$A$5:$A$16,0)) -> Equipo Tandem | K77: =INDEX(Tareas!$G$6:$G$37,MATCH($A77,Tareas!$A$6:$A$37,0)) -> 118 | L77: =INDEX(Tareas!$H$6:$H$37,MATCH($A77,Tareas!$A$6:$A$37,0)) -> 138
A78: 5.4 | B78: =INDEX(Tareas!$B$6:$B$37,MATCH($A78,Tareas!$A$6:$A$37,0)) -> Go-live y estabilización (4 semanas) | C78: OPS | D78: =INDEX(Recursos!$B$5:$B$16,MATCH($C78,Recursos!$A$5:$A$16,0)) -> Ingeniero/a DevOps (Tandem) | E78: 0.5 | F78: =INDEX(Tareas!$D$6:$D$37,MATCH($A78,Tareas!$A$6:$A$37,0)) -> 20 | G78: =E78*F78 -> 10 | H78: =INDEX(Recursos!$D$5:$D$16,MATCH($C78,Recursos!$A$5:$A$16,0)) -> 460 | I78: =G78*H78 -> 4600 | J78: =INDEX(Recursos!$C$5:$C$16,MATCH($C78,Recursos!$A$5:$A$16,0)) -> Ambientes | K78: =INDEX(Tareas!$G$6:$G$37,MATCH($A78,Tareas!$A$6:$A$37,0)) -> 118 | L78: =INDEX(Tareas!$H$6:$H$37,MATCH($A78,Tareas!$A$6:$A$37,0)) -> 138
A79: 5.4 | B79: =INDEX(Tareas!$B$6:$B$37,MATCH($A79,Tareas!$A$6:$A$37,0)) -> Go-live y estabilización (4 semanas) | C79: UX | D79: =INDEX(Recursos!$B$5:$B$16,MATCH($C79,Recursos!$A$5:$A$16,0)) -> Diseñador/a UX/UI (Tandem) | E79: 0.2 | F79: =INDEX(Tareas!$D$6:$D$37,MATCH($A79,Tareas!$A$6:$A$37,0)) -> 20 | G79: =E79*F79 -> 4 | H79: =INDEX(Recursos!$D$5:$D$16,MATCH($C79,Recursos!$A$5:$A$16,0)) -> 420 | I79: =G79*H79 -> 1680 | J79: =INDEX(Recursos!$C$5:$C$16,MATCH($C79,Recursos!$A$5:$A$16,0)) -> Equipo Tandem | K79: =INDEX(Tareas!$G$6:$G$37,MATCH($A79,Tareas!$A$6:$A$37,0)) -> 118 | L79: =INDEX(Tareas!$H$6:$H$37,MATCH($A79,Tareas!$A$6:$A$37,0)) -> 138
A80: 5.4 | B80: =INDEX(Tareas!$B$6:$B$37,MATCH($A80,Tareas!$A$6:$A$37,0)) -> Go-live y estabilización (4 semanas) | C80: TEC | D80: =INDEX(Recursos!$B$5:$B$16,MATCH($C80,Recursos!$A$5:$A$16,0)) -> Tecnología VCA (P. Guzmán) | E80: 0.3 | F80: =INDEX(Tareas!$D$6:$D$37,MATCH($A80,Tareas!$A$6:$A$37,0)) -> 20 | G80: =E80*F80 -> 6 | H80: =INDEX(Recursos!$D$5:$D$16,MATCH($C80,Recursos!$A$5:$A$16,0)) -> 190 | I80: =G80*H80 -> 1140 | J80: =INDEX(Recursos!$C$5:$C$16,MATCH($C80,Recursos!$A$5:$A$16,0)) -> Horas VCA | K80: =INDEX(Tareas!$G$6:$G$37,MATCH($A80,Tareas!$A$6:$A$37,0)) -> 118 | L80: =INDEX(Tareas!$H$6:$H$37,MATCH($A80,Tareas!$A$6:$A$37,0)) -> 138
A81: 5.4 | B81: =INDEX(Tareas!$B$6:$B$37,MATCH($A81,Tareas!$A$6:$A$37,0)) -> Go-live y estabilización (4 semanas) | C81: RH | D81: =INDEX(Recursos!$B$5:$B$16,MATCH($C81,Recursos!$A$5:$A$16,0)) -> RR.HH. VCA (S. Ibarra / referente) | E81: 0.5 | F81: =INDEX(Tareas!$D$6:$D$37,MATCH($A81,Tareas!$A$6:$A$37,0)) -> 20 | G81: =E81*F81 -> 10 | H81: =INDEX(Recursos!$D$5:$D$16,MATCH($C81,Recursos!$A$5:$A$16,0)) -> 160 | I81: =G81*H81 -> 1600 | J81: =INDEX(Recursos!$C$5:$C$16,MATCH($C81,Recursos!$A$5:$A$16,0)) -> Horas VCA | K81: =INDEX(Tareas!$G$6:$G$37,MATCH($A81,Tareas!$A$6:$A$37,0)) -> 118 | L81: =INDEX(Tareas!$H$6:$H$37,MATCH($A81,Tareas!$A$6:$A$37,0)) -> 138
A82: 5.5 | B82: =INDEX(Tareas!$B$6:$B$37,MATCH($A82,Tareas!$A$6:$A$37,0)) -> Tablero y transferencia del seguimiento | C82: PO | D82: =INDEX(Recursos!$B$5:$B$16,MATCH($C82,Recursos!$A$5:$A$16,0)) -> Product Owner (Tandem) | E82: 0.3 | F82: =INDEX(Tareas!$D$6:$D$37,MATCH($A82,Tareas!$A$6:$A$37,0)) -> 10 | G82: =E82*F82 -> 3 | H82: =INDEX(Recursos!$D$5:$D$16,MATCH($C82,Recursos!$A$5:$A$16,0)) -> 480 | I82: =G82*H82 -> 1440 | J82: =INDEX(Recursos!$C$5:$C$16,MATCH($C82,Recursos!$A$5:$A$16,0)) -> Equipo Tandem | K82: =INDEX(Tareas!$G$6:$G$37,MATCH($A82,Tareas!$A$6:$A$37,0)) -> 130 | L82: =INDEX(Tareas!$H$6:$H$37,MATCH($A82,Tareas!$A$6:$A$37,0)) -> 140
A83: 5.5 | B83: =INDEX(Tareas!$B$6:$B$37,MATCH($A83,Tareas!$A$6:$A$37,0)) -> Tablero y transferencia del seguimiento | C83: DEV | D83: =INDEX(Recursos!$B$5:$B$16,MATCH($C83,Recursos!$A$5:$A$16,0)) -> Desarrollador/a full-stack (Tandem) | E83: 0.3 | F83: =INDEX(Tareas!$D$6:$D$37,MATCH($A83,Tareas!$A$6:$A$37,0)) -> 10 | G83: =E83*F83 -> 3 | H83: =INDEX(Recursos!$D$5:$D$16,MATCH($C83,Recursos!$A$5:$A$16,0)) -> 440 | I83: =G83*H83 -> 1320 | J83: =INDEX(Recursos!$C$5:$C$16,MATCH($C83,Recursos!$A$5:$A$16,0)) -> Equipo Tandem | K83: =INDEX(Tareas!$G$6:$G$37,MATCH($A83,Tareas!$A$6:$A$37,0)) -> 130 | L83: =INDEX(Tareas!$H$6:$H$37,MATCH($A83,Tareas!$A$6:$A$37,0)) -> 140
A84: 5.5 | B84: =INDEX(Tareas!$B$6:$B$37,MATCH($A84,Tareas!$A$6:$A$37,0)) -> Tablero y transferencia del seguimiento | C84: RH | D84: =INDEX(Recursos!$B$5:$B$16,MATCH($C84,Recursos!$A$5:$A$16,0)) -> RR.HH. VCA (S. Ibarra / referente) | E84: 0.4 | F84: =INDEX(Tareas!$D$6:$D$37,MATCH($A84,Tareas!$A$6:$A$37,0)) -> 10 | G84: =E84*F84 -> 4 | H84: =INDEX(Recursos!$D$5:$D$16,MATCH($C84,Recursos!$A$5:$A$16,0)) -> 160 | I84: =G84*H84 -> 640 | J84: =INDEX(Recursos!$C$5:$C$16,MATCH($C84,Recursos!$A$5:$A$16,0)) -> Horas VCA | K84: =INDEX(Tareas!$G$6:$G$37,MATCH($A84,Tareas!$A$6:$A$37,0)) -> 130 | L84: =INDEX(Tareas!$H$6:$H$37,MATCH($A84,Tareas!$A$6:$A$37,0)) -> 140
A85: 5.5 | B85: =INDEX(Tareas!$B$6:$B$37,MATCH($A85,Tareas!$A$6:$A$37,0)) -> Tablero y transferencia del seguimiento | C85: TEC | D85: =INDEX(Recursos!$B$5:$B$16,MATCH($C85,Recursos!$A$5:$A$16,0)) -> Tecnología VCA (P. Guzmán) | E85: 0.2 | F85: =INDEX(Tareas!$D$6:$D$37,MATCH($A85,Tareas!$A$6:$A$37,0)) -> 10 | G85: =E85*F85 -> 2 | H85: =INDEX(Recursos!$D$5:$D$16,MATCH($C85,Recursos!$A$5:$A$16,0)) -> 190 | I85: =G85*H85 -> 380 | J85: =INDEX(Recursos!$C$5:$C$16,MATCH($C85,Recursos!$A$5:$A$16,0)) -> Horas VCA | K85: =INDEX(Tareas!$G$6:$G$37,MATCH($A85,Tareas!$A$6:$A$37,0)) -> 130 | L85: =INDEX(Tareas!$H$6:$H$37,MATCH($A85,Tareas!$A$6:$A$37,0)) -> 140
... A88: 5.6 | B88: =INDEX(Tareas!$B$6:$B$37,MATCH($A88,Tareas!$A$6:$A$37,0)) -> Informe de ocupación y recomendación | C88: SG | D88: =INDEX(Recursos!$B$5:$B$16,MATCH($C88,Recursos!$A$5:$A$16,0)) -> Servicios Generales VCA (D. Sosa) | E88: 0.5 | F88: =INDEX(Tareas!$D$6:$D$37,MATCH($A88,Tareas!$A$6:$A$37,0)) -> 10 | G88: =E88*F88 -> 5 | H88: =INDEX(Recursos!$D$5:$D$16,MATCH($C88,Recursos!$A$5:$A$16,0)) -> 170 | I88: =G88*H88 -> 850 | J88: =INDEX(Recursos!$C$5:$C$16,MATCH($C88,Recursos!$A$5:$A$16,0)) -> Horas VCA | K88: =INDEX(Tareas!$G$6:$G$37,MATCH($A88,Tareas!$A$6:$A$37,0)) -> 130 | L88: =INDEX(Tareas!$H$6:$H$37,MATCH($A88,Tareas!$A$6:$A$37,0)) -> 140
A89: Total mano de obra | G89: =SUM(G5:G88) -> 596.1 | I89: =SUM(I5:I88) -> 235926

Sheet Partidas
A1: Partidas no laborales: cantidad × precio unitario
A2: Cada partida tiene su base unitaria y el período en que se devenga. Los precios son supuestos de simulación a validar con cotizaciones (excepto la licencia, derivada de la N1).
A4: ID | B4: Concepto | C4: Línea de costo (N1) | D4: Cantidad | E4: Unidad | F4: Precio unitario USD | G4: Costo USD | H4: Devenga desde (inicio de tarea) | I4: Hasta (fin de tarea) | J4: Inicio | K4: Fin | L4: Nota
A5: P-1 | B5: Licencia WorkHub, 1.200 usuarios nominados (primer año de soporte incluido) | C5: Licencia | D5: 1200 | E5: usuarios | F5: 90 | G5: =D5*F5 -> 108000 | H5: 1.1 | I5: 1.1 | J5: =INDEX(Tareas!$M$6:$M$37,MATCH(H5,Tareas!$A$6:$A$37,0)) -> 46296 | K5: =J5 -> 46296 | L5: Cotización de licenciante: USD 108.000 / 1.200 usuarios (N1).
A6: P-2a | B6: Entorno de desarrollo (Azure Brasil Sur) | C6: Ambientes | D6: 7 | E6: meses | F6: 150 | G6: =D6*F6 -> 1050 | H6: 5.1 | I6: 1.6 | J6: =INDEX(Tareas!$M$6:$M$37,MATCH(H6,Tareas!$A$6:$A$37,0)) -> 46309 | K6: =INDEX(Tareas!$N$6:$N$37,MATCH(I6,Tareas!$A$6:$A$37,0)) -> 46507 | L6: Supuesto de simulación a validar con cotización de VCA.
A7: P-2b | B7: Entorno de QA / staging | C7: Ambientes | D7: 6 | E7: meses | F7: 250 | G7: =D7*F7 -> 1500 | H7: 5.1 | I7: 5.4 | J7: =INDEX(Tareas!$M$6:$M$37,MATCH(H7,Tareas!$A$6:$A$37,0)) -> 46309 | K7: =INDEX(Tareas!$N$6:$N$37,MATCH(I7,Tareas!$A$6:$A$37,0)) -> 46505 | L7: Ídem.
A8: P-2c | B8: Entorno de producción (alineado al hosting anual de N1: USD 5.060 / 12) | C8: Ambientes | D8: 2 | E8: meses | F8: 422 | G8: =D8*F8 -> 844 | H8: 5.4 | I8: 1.6 | J8: =INDEX(Tareas!$M$6:$M$37,MATCH(H8,Tareas!$A$6:$A$37,0)) -> 46477 | K8: =INDEX(Tareas!$N$6:$N$37,MATCH(I8,Tareas!$A$6:$A$37,0)) -> 46507 | L8: Ídem; desde preproducción de marzo.
A9: P-2d | B9: Observabilidad y logs (APM) | C9: Ambientes | D9: 7 | E9: meses | F9: 300 | G9: =D9*F9 -> 2100 | H9: 5.1 | I9: 1.6 | J9: =INDEX(Tareas!$M$6:$M$37,MATCH(H9,Tareas!$A$6:$A$37,0)) -> 46309 | K9: =INDEX(Tareas!$N$6:$N$37,MATCH(I9,Tareas!$A$6:$A$37,0)) -> 46507 | L9: Ídem.
A10: P-2e | B10: Herramientas de soporte del equipo (CI/CD, backlog, bóveda de secretos) | C10: Ambientes | D10: 42 | E10: usuario-mes | F10: 40 | G10: =D10*F10 -> 1680 | H10: 5.1 | I10: 1.6 | J10: =INDEX(Tareas!$M$6:$M$37,MATCH(H10,Tareas!$A$6:$A$37,0)) -> 46309 | K10: =INDEX(Tareas!$N$6:$N$37,MATCH(I10,Tareas!$A$6:$A$37,0)) -> 46507 | L10: 6 usuarios x 7 meses.
A11: P-3a | B11: Piezas de la campaña de lanzamiento (diseño y producción) | C11: Gestión del cambio | D11: 12 | E11: piezas | F11: 300 | G11: =D11*F11 -> 3600 | H11: 4.3 | I11: 4.3 | J11: =INDEX(Tareas!$M$6:$M$37,MATCH(H11,Tareas!$A$6:$A$37,0)) -> 46447 | K11: =INDEX(Tareas!$N$6:$N$37,MATCH(I11,Tareas!$A$6:$A$37,0)) -> 46465 | L11: Supuesto de simulación.
A12: P-3b | B12: Materiales de capacitación (video-tutoriales y guías) | C12: Gestión del cambio | D12: 8 | E12: materiales | F12: 450 | G12: =D12*F12 -> 3600 | H12: 4.4 | I12: 4.5 | J12: =INDEX(Tareas!$M$6:$M$37,MATCH(H12,Tareas!$A$6:$A$37,0)) -> 46336 | K12: =INDEX(Tareas!$N$6:$N$37,MATCH(I12,Tareas!$A$6:$A$37,0)) -> 46373 | L12: Ídem.
A13: P-3c | B13: Sesiones de capacitación a 1.200 colaboradores (logística) | C13: Gestión del cambio | D13: 30 | E13: sesiones | F13: 120 | G13: =D13*F13 -> 3600 | H13: 4.4 | I13: 4.5 | J13: =INDEX(Tareas!$M$6:$M$37,MATCH(H13,Tareas!$A$6:$A$37,0)) -> 46336 | K13: =INDEX(Tareas!$N$6:$N$37,MATCH(I13,Tareas!$A$6:$A$37,0)) -> 46373 | L13: Ídem; los referentes capacitados replican.
A14: P-3d | B14: Encuestas de intención de uso y pulso | C14: Gestión del cambio | D14: 1 | E14: servicio | F14: 900 | G14: =D14*F14 -> 900 | H14: 4.1 | I14: 4.1 | J14: =INDEX(Tareas!$M$6:$M$37,MATCH(H14,Tareas!$A$6:$A$37,0)) -> 46308 | K14: =INDEX(Tareas!$N$6:$N$37,MATCH(I14,Tareas!$A$6:$A$37,0)) -> 46321 | L14: Ídem.
A15: P-4a | B15: Prueba de intrusión externa (requisito RA-2) | C15: Integraciones | D15: 1 | E15: servicio | F15: 7500 | G15: =D15*F15 -> 7500 | H15: 3.4 | I15: 3.4 | J15: =INDEX(Tareas!$M$6:$M$37,MATCH(H15,Tareas!$A$6:$A$37,0)) -> 46339 | K15: =INDEX(Tareas!$N$6:$N$37,MATCH(I15,Tareas!$A$6:$A$37,0)) -> 46360 | L15: Supuesto de simulación.
A16: P-4b | B16: Entornos sandbox de conectores (HRIS y Exchange) | C16: Integraciones | D16: 2 | E16: conectores | F16: 1200 | G16: =D16*F16 -> 2400 | H16: 3.1 | I16: 3.3 | J16: =INDEX(Tareas!$M$6:$M$37,MATCH(H16,Tareas!$A$6:$A$37,0)) -> 46309 | K16: =INDEX(Tareas!$N$6:$N$37,MATCH(I16,Tareas!$A$6:$A$37,0)) -> 46338 | L16: Ídem.
A17: Total partidas | G17: =SUM(G5:G16) -> 136774
B19: P-1 se devenga íntegra a la firma del Acta (H-0). El resto se distribuye linealmente por día hábil entre las fechas indicadas.

Sheet Presupuesto
A1: Presupuesto preliminar y línea base de costos
A2: La estimación ascendente (tarea por tarea) se compara con la descendente de la N1 sin ajustarla. Montos en USD.
A4: A. Conciliación de la estimación ascendente con la descendente de la N1
A5: Línea de costo | B5: N1 (descendente) | C5: N2 mano de obra | D5: N2 partidas no laborales | E5: N2 total (ascendente) | F5: Diferencia | G5: Diferencia %
A6: Licencia | B6: 108000 | C6: =SUMIF(Costos!$J$5:$J$88,A6,Costos!$I$5:$I$88) -> 0 | D6: =SUMIF(Partidas!$C$5:$C$16,A6,Partidas!$G$5:$G$16) -> 108000 | E6: =C6+D6 -> 108000 | F6: =E6-B6 -> 0 | G6: =F6/B6 -> 0
A7: Equipo Tandem | B7: 168000 | C7: =SUMIF(Costos!$J$5:$J$88,A7,Costos!$I$5:$I$88) -> 148412 | D7: =SUMIF(Partidas!$C$5:$C$16,A7,Partidas!$G$5:$G$16) -> 0 | E7: =C7+D7 -> 148412 | F7: =E7-B7 -> -19588 | G7: =F7/B7 -> -0.11659524
A8: Integraciones | B8: 46000 | C8: =SUMIF(Costos!$J$5:$J$88,A8,Costos!$I$5:$I$88) -> 34080 | D8: =SUMIF(Partidas!$C$5:$C$16,A8,Partidas!$G$5:$G$16) -> 9900 | E8: =C8+D8 -> 43980 | F8: =E8-B8 -> -2020 | G8: =F8/B8 -> -0.043913043
A9: Ambientes | B9: 22000 | C9: =SUMIF(Costos!$J$5:$J$88,A9,Costos!$I$5:$I$88) -> 10396 | D9: =SUMIF(Partidas!$C$5:$C$16,A9,Partidas!$G$5:$G$16) -> 7174 | E9: =C9+D9 -> 17570 | F9: =E9-B9 -> -4430 | G9: =F9/B9 -> -0.20136364
A10: Gestión del cambio | B10: 38000 | C10: =SUMIF(Costos!$J$5:$J$88,A10,Costos!$I$5:$I$88) -> 24000 | D10: =SUMIF(Partidas!$C$5:$C$16,A10,Partidas!$G$5:$G$16) -> 11700 | E10: =C10+D10 -> 35700 | F10: =E10-B10 -> -2300 | G10: =F10/B10 -> -0.060526316
A11: Horas VCA | B11: 16000 | C11: =SUMIF(Costos!$J$5:$J$88,A11,Costos!$I$5:$I$88) -> 19038 | D11: =SUMIF(Partidas!$C$5:$C$16,A11,Partidas!$G$5:$G$16) -> 0 | E11: =C11+D11 -> 19038 | F11: =E11-B11 -> 3038 | G11: =F11/B11 -> 0.189875
A12: Costo base de actividades | B12: =SUM(B6:B11) -> 398000 | C12: =SUM(C6:C11) -> 235926 | D12: =SUM(D6:D11) -> 136774 | E12: =SUM(E6:E11) -> 372700 | F12: =SUM(F6:F11) -> -25300 | G12: =F12/B12 -> -0.063567839
A13: Control: N1 = costo base declarado (USD 398.000) | B13: =IF(B12=CostoBaseN1,"OK","REVISAR") -> OK
A14: ¿La ascendente valida a la descendente? (|dif.| ≤ tolerancia) | B14: =IF(ABS(G12)<=Tolerancia,"Sí: dentro de ±"&TEXT(Tolerancia,"0%"),"No") -> Sí: dentro de ±10%
A16: B. Línea base de costos, reservas y presupuesto del proyecto
A17: Concepto | B17: USD | C17: Nota
A18: Costo base de actividades (ascendente) | B18: =E12 -> 372700 | C18: Suma de mano de obra y partidas no laborales; no se iguala a la N1.
A19: Reserva para contingencias | B19: =Contingencia -> 22000 | C19: Dentro de la línea base. Respuesta a riesgos identificados; la autoriza el PM hasta USD 5.000 por evento.
A20: Línea base de costos | B20: =B18+B19 -> 394700 | C20: Referencia para medir el desempeño (EVM, N4).
A21: Reserva de gestión (fuera de la línea base) | B21: =PctRG*B20 -> 15788 | C21: Trabajo imprevisto dentro del alcance; la administra el Comité y se libera por solicitud de cambio.
A22: Presupuesto del proyecto | B22: =B20+B21 -> 410488 | C22: Línea base + reserva de gestión.
A23: Presupuesto autorizado en el Acta (N1) | B23: =Autorizado -> 420000 | C23: Techo de autorización hasta la ratificación en H-1.
A24: Margen autorizado sin asignar | B24: =B23-B22 -> 9512 | C24: No se gasta ni se redistribuye sin solicitud de cambio.
A25: Banda de tolerancia — límite inferior | B25: =Autorizado*(1-Tolerancia) -> 378000 | C25: Referencia de variación, no obligación de gasto.
A26: Banda de tolerancia — límite superior | B26: =Autorizado*(1+Tolerancia) -> 462000 | C26: Superarlo exige una nueva línea base aprobada por el Comité.
A27: Control: la línea base está dentro de la banda | B27: =IF(AND(B20>=B25,B20<=B26),"OK","REVISAR") -> OK
A30: C. Costo por tarea y distribución mensual de la línea base
A31: ID | B31: Concepto | C31: Costo USD | D31: Inicio | E31: Fin | F31: 46296 | G31: 46327 | H31: 46357 | I31: 46388 | J31: 46419 | K31: 46447 | L31: 46478
B32: (fin de mes) | F32: =EOMONTH(F31,0) -> 46326 | G32: =EOMONTH(G31,0) -> 46356 | H32: =EOMONTH(H31,0) -> 46387 | I32: =EOMONTH(I31,0) -> 46418 | J32: =EOMONTH(J31,0) -> 46446 | K32: =EOMONTH(K31,0) -> 46477 | L32: =EOMONTH(L31,0) -> 46507
A33: 1.1 | B33: =INDEX(Tareas!$B$6:$B$37,MATCH(A33,Tareas!$A$6:$A$37,0)) -> Acta de constitución | C33: =SUMIF(Costos!$A$5:$A$88,A33,Costos!$I$5:$I$88) -> 1040 | D33: =INDEX(Tareas!$M$6:$M$37,MATCH(A33,Tareas!$A$6:$A$37,0)) -> 46296 | E33: =INDEX(Tareas!$N$6:$N$37,MATCH(A33,Tareas!$A$6:$A$37,0)) -> 46297 | F33: =IF(OR($E33<F$31,$D33>F$32),0,$C33*NETWORKDAYS(MAX($D33,F$31),MIN($E33,F$32),Feriados)/NETWORKDAYS($D33,$E33,Feriados)) -> 1040 | G33: =IF(OR($E33<G$31,$D33>G$32),0,$C33*NETWORKDAYS(MAX($D33,G$31),MIN($E33,G$32),Feriados)/NETWORKDAYS($D33,$E33,Feriados)) -> 0 | H33: =IF(OR($E33<H$31,$D33>H$32),0,$C33*NETWORKDAYS(MAX($D33,H$31),MIN($E33,H$32),Feriados)/NETWORKDAYS($D33,$E33,Feriados)) -> 0 | I33: =IF(OR($E33<I$31,$D33>I$32),0,$C33*NETWORKDAYS(MAX($D33,I$31),MIN($E33,I$32),Feriados)/NETWORKDAYS($D33,$E33,Feriados)) -> 0 | J33: =IF(OR($E33<J$31,$D33>J$32),0,$C33*NETWORKDAYS(MAX($D33,J$31),MIN($E33,J$32),Feriados)/NETWORKDAYS($D33,$E33,Feriados)) -> 0 | K33: =IF(OR($E33<K$31,$D33>K$32),0,$C33*NETWORKDAYS(MAX($D33,K$31),MIN($E33,K$32),Feriados)/NETWORKDAYS($D33,$E33,Feriados)) -> 0 | L33: =IF(OR($E33<L$31,$D33>L$32),0,$C33*NETWORKDAYS(MAX($D33,L$31),MIN($E33,L$32),Feriados)/NETWORKDAYS($D33,$E33,Feriados)) -> 0
A34: 1.2 | B34: =INDEX(Tareas!$B$6:$B$37,MATCH(A34,Tareas!$A$6:$A$37,0)) -> Declaración del alcance y EDT | C34: =SUMIF(Costos!$A$5:$A$88,A34,Costos!$I$5:$I$88) -> 2136 | D34: =INDEX(Tareas!$M$6:$M$37,MATCH(A34,Tareas!$A$6:$A$37,0)) -> 46300 | E34: =INDEX(Tareas!$N$6:$N$37,MATCH(A34,Tareas!$A$6:$A$37,0)) -> 46308 | F34: =IF(OR($E34<F$31,$D34>F$32),0,$C34*NETWORKDAYS(MAX($D34,F$31),MIN($E34,F$32),Feriados)/NETWORKDAYS($D34,$E34,Feriados)) -> 2136 | G34: =IF(OR($E34<G$31,$D34>G$32),0,$C34*NETWORKDAYS(MAX($D34,G$31),MIN($E34,G$32),Feriados)/NETWORKDAYS($D34,$E34,Feriados)) -> 0 | H34: =IF(OR($E34<H$31,$D34>H$32),0,$C34*NETWORKDAYS(MAX($D34,H$31),MIN($E34,H$32),Feriados)/NETWORKDAYS($D34,$E34,Feriados)) -> 0 | I34: =IF(OR($E34<I$31,$D34>I$32),0,$C34*NETWORKDAYS(MAX($D34,I$31),MIN($E34,I$32),Feriados)/NETWORKDAYS($D34,$E34,Feriados)) -> 0 | J34: =IF(OR($E34<J$31,$D34>J$32),0,$C34*NETWORKDAYS(MAX($D34,J$31),MIN($E34,J$32),Feriados)/NETWORKDAYS($D34,$E34,Feriados)) -> 0 | K34: =IF(OR($E34<K$31,$D34>K$32),0,$C34*NETWORKDAYS(MAX($D34,K$31),MIN($E34,K$32),Feriados)/NETWORKDAYS($D34,$E34,Feriados)) -> 0 | L34: =IF(OR($E34<L$31,$D34>L$32),0,$C34*NETWORKDAYS(MAX($D34,L$31),MIN($E34,L$32),Feriados)/NETWORKDAYS($D34,$E34,Feriados)) -> 0
A35: 1.3 | B35: =INDEX(Tareas!$B$6:$B$37,MATCH(A35,Tareas!$A$6:$A$37,0)) -> Cronograma, presupuesto y línea base | C35: =SUMIF(Costos!$A$5:$A$88,A35,Costos!$I$5:$I$88) -> 936 | D35: =INDEX(Tareas!$M$6:$M$37,MATCH(A35,Tareas!$A$6:$A$37,0)) -> 46300 | E35: =INDEX(Tareas!$N$6:$N$37,MATCH(A35,Tareas!$A$6:$A$37,0)) -> 46308 | F35: =IF(OR($E35<F$31,$D35>F$32),0,$C35*NETWORKDAYS(MAX($D35,F$31),MIN($E35,F$32),Feriados)/NETWORKDAYS($D35,$E35,Feriados)) -> 936 | G35: =IF(OR($E35<G$31,$D35>G$32),0,$C35*NETWORKDAYS(MAX($D35,G$31),MIN($E35,G$32),Feriados)/NETWORKDAYS($D35,$E35,Feriados)) -> 0 | H35: =IF(OR($E35<H$31,$D35>H$32),0,$C35*NETWORKDAYS(MAX($D35,H$31),MIN($E35,H$32),Feriados)/NETWORKDAYS($D35,$E35,Feriados)) -> 0 | I35: =IF(OR($E35<I$31,$D35>I$32),0,$C35*NETWORKDAYS(MAX($D35,I$31),MIN($E35,I$32),Feriados)/NETWORKDAYS($D35,$E35,Feriados)) -> 0 | J35: =IF(OR($E35<J$31,$D35>J$32),0,$C35*NETWORKDAYS(MAX($D35,J$31),MIN($E35,J$32),Feriados)/NETWORKDAYS($D35,$E35,Feriados)) -> 0 | K35: =IF(OR($E35<K$31,$D35>K$32),0,$C35*NETWORKDAYS(MAX($D35,K$31),MIN($E35,K$32),Feriados)/NETWORKDAYS($D35,$E35,Feriados)) -> 0 | L35: =IF(OR($E35<L$31,$D35>L$32),0,$C35*NETWORKDAYS(MAX($D35,L$31),MIN($E35,L$32),Feriados)/NETWORKDAYS($D35,$E35,Feriados)) -> 0
A36: 1.4 | B36: =INDEX(Tareas!$B$6:$B$37,MATCH(A36,Tareas!$A$6:$A$37,0)) -> Registro de riesgos e interesados | C36: =SUMIF(Costos!$A$5:$A$88,A36,Costos!$I$5:$I$88) -> 600 | D36: =INDEX(Tareas!$M$6:$M$37,MATCH(A36,Tareas!$A$6:$A$37,0)) -> 46300 | E36: =INDEX(Tareas!$N$6:$N$37,MATCH(A36,Tareas!$A$6:$A$37,0)) -> 46304 | F36: =IF(OR($E36<F$31,$D36>F$32),0,$C36*NETWORKDAYS(MAX($D36,F$31),MIN($E36,F$32),Feriados)/NETWORKDAYS($D36,$E36,Feriados)) -> 600 | G36: =IF(OR($E36<G$31,$D36>G$32),0,$C36*NETWORKDAYS(MAX($D36,G$31),MIN($E36,G$32),Feriados)/NETWORKDAYS($D36,$E36,Feriados)) -> 0 | H36: =IF(OR($E36<H$31,$D36>H$32),0,$C36*NETWORKDAYS(MAX($D36,H$31),MIN($E36,H$32),Feriados)/NETWORKDAYS($D36,$E36,Feriados)) -> 0 | I36: =IF(OR($E36<I$31,$D36>I$32),0,$C36*NETWORKDAYS(MAX($D36,I$31),MIN($E36,I$32),Feriados)/NETWORKDAYS($D36,$E36,Feriados)) -> 0 | J36: =IF(OR($E36<J$31,$D36>J$32),0,$C36*NETWORKDAYS(MAX($D36,J$31),MIN($E36,J$32),Feriados)/NETWORKDAYS($D36,$E36,Feriados)) -> 0 | K36: =IF(OR($E36<K$31,$D36>K$32),0,$C36*NETWORKDAYS(MAX($D36,K$31),MIN($E36,K$32),Feriados)/NETWORKDAYS($D36,$E36,Feriados)) -> 0 | L36: =IF(OR($E36<L$31,$D36>L$32),0,$C36*NETWORKDAYS(MAX($D36,L$31),MIN($E36,L$32),Feriados)/NETWORKDAYS($D36,$E36,Feriados)) -> 0
A37: 1.5 | B37: =INDEX(Tareas!$B$6:$B$37,MATCH(A37,Tareas!$A$6:$A$37,0)) -> Seguimiento, cambios e informes (tarea resumen) | C37: =SUMIF(Costos!$A$5:$A$88,A37,Costos!$I$5:$I$88) -> 34320 | D37: =INDEX(Tareas!$M$6:$M$37,MATCH(A37,Tareas!$A$6:$A$37,0)) -> 46309 | E37: =INDEX(Tareas!$N$6:$N$37,MATCH(A37,Tareas!$A$6:$A$37,0)) -> 46507 | F37: =IF(OR($E37<F$31,$D37>F$32),0,$C37*NETWORKDAYS(MAX($D37,F$31),MIN($E37,F$32),Feriados)/NETWORKDAYS($D37,$E37,Feriados)) -> 3380 | G37: =IF(OR($E37<G$31,$D37>G$32),0,$C37*NETWORKDAYS(MAX($D37,G$31),MIN($E37,G$32),Feriados)/NETWORKDAYS($D37,$E37,Feriados)) -> 5200 | H37: =IF(OR($E37<H$31,$D37>H$32),0,$C37*NETWORKDAYS(MAX($D37,H$31),MIN($E37,H$32),Feriados)/NETWORKDAYS($D37,$E37,Feriados)) -> 5200 | I37: =IF(OR($E37<I$31,$D37>I$32),0,$C37*NETWORKDAYS(MAX($D37,I$31),MIN($E37,I$32),Feriados)/NETWORKDAYS($D37,$E37,Feriados)) -> 5200 | J37: =IF(OR($E37<J$31,$D37>J$32),0,$C37*NETWORKDAYS(MAX($D37,J$31),MIN($E37,J$32),Feriados)/NETWORKDAYS($D37,$E37,Feriados)) -> 4680 | K37: =IF(OR($E37<K$31,$D37>K$32),0,$C37*NETWORKDAYS(MAX($D37,K$31),MIN($E37,K$32),Feriados)/NETWORKDAYS($D37,$E37,Feriados)) -> 5200 | L37: =IF(OR($E37<L$31,$D37>L$32),0,$C37*NETWORKDAYS(MAX($D37,L$31),MIN($E37,L$32),Feriados)/NETWORKDAYS($D37,$E37,Feriados)) -> 5460
A38: 1.6 | B38: =INDEX(Tareas!$B$6:$B$37,MATCH(A38,Tareas!$A$6:$A$37,0)) -> Cierre y lecciones aprendidas | C38: =SUMIF(Costos!$A$5:$A$88,A38,Costos!$I$5:$I$88) -> 1020 | D38: =INDEX(Tareas!$M$6:$M$37,MATCH(A38,Tareas!$A$6:$A$37,0)) -> 46503 | E38: =INDEX(Tareas!$N$6:$N$37,MATCH(A38,Tareas!$A$6:$A$37,0)) -> 46507 | F38: =IF(OR($E38<F$31,$D38>F$32),0,$C38*NETWORKDAYS(MAX($D38,F$31),MIN($E38,F$32),Feriados)/NETWORKDAYS($D38,$E38,Feriados)) -> 0 | G38: =IF(OR($E38<G$31,$D38>G$32),0,$C38*NETWORKDAYS(MAX($D38,G$31),MIN($E38,G$32),Feriados)/NETWORKDAYS($D38,$E38,Feriados)) -> 0 | H38: =IF(OR($E38<H$31,$D38>H$32),0,$C38*NETWORKDAYS(MAX($D38,H$31),MIN($E38,H$32),Feriados)/NETWORKDAYS($D38,$E38,Feriados)) -> 0 | I38: =IF(OR($E38<I$31,$D38>I$32),0,$C38*NETWORKDAYS(MAX($D38,I$31),MIN($E38,I$32),Feriados)/NETWORKDAYS($D38,$E38,Feriados)) -> 0 | J38: =IF(OR($E38<J$31,$D38>J$32),0,$C38*NETWORKDAYS(MAX($D38,J$31),MIN($E38,J$32),Feriados)/NETWORKDAYS($D38,$E38,Feriados)) -> 0 | K38: =IF(OR($E38<K$31,$D38>K$32),0,$C38*NETWORKDAYS(MAX($D38,K$31),MIN($E38,K$32),Feriados)/NETWORKDAYS($D38,$E38,Feriados)) -> 0 | L38: =IF(OR($E38<L$31,$D38>L$32),0,$C38*NETWORKDAYS(MAX($D38,L$31),MIN($E38,L$32),Feriados)/NETWORKDAYS($D38,$E38,Feriados)) -> 1020
A39: 2.1 | B39: =INDEX(Tareas!$B$6:$B$37,MATCH(A39,Tareas!$A$6:$A$37,0)) -> Relevamiento y reglas de negocio | C39: =SUMIF(Costos!$A$5:$A$88,A39,Costos!$I$5:$I$88) -> 7060 | D39: =INDEX(Tareas!$M$6:$M$37,MATCH(A39,Tareas!$A$6:$A$37,0)) -> 46309 | E39: =INDEX(Tareas!$N$6:$N$37,MATCH(A39,Tareas!$A$6:$A$37,0)) -> 46322 | F39: =IF(OR($E39<F$31,$D39>F$32),0,$C39*NETWORKDAYS(MAX($D39,F$31),MIN($E39,F$32),Feriados)/NETWORKDAYS($D39,$E39,Feriados)) -> 7060 | G39: =IF(OR($E39<G$31,$D39>G$32),0,$C39*NETWORKDAYS(MAX($D39,G$31),MIN($E39,G$32),Feriados)/NETWORKDAYS($D39,$E39,Feriados)) -> 0 | H39: =IF(OR($E39<H$31,$D39>H$32),0,$C39*NETWORKDAYS(MAX($D39,H$31),MIN($E39,H$32),Feriados)/NETWORKDAYS($D39,$E39,Feriados)) -> 0 | I39: =IF(OR($E39<I$31,$D39>I$32),0,$C39*NETWORKDAYS(MAX($D39,I$31),MIN($E39,I$32),Feriados)/NETWORKDAYS($D39,$E39,Feriados)) -> 0 | J39: =IF(OR($E39<J$31,$D39>J$32),0,$C39*NETWORKDAYS(MAX($D39,J$31),MIN($E39,J$32),Feriados)/NETWORKDAYS($D39,$E39,Feriados)) -> 0 | K39: =IF(OR($E39<K$31,$D39>K$32),0,$C39*NETWORKDAYS(MAX($D39,K$31),MIN($E39,K$32),Feriados)/NETWORKDAYS($D39,$E39,Feriados)) -> 0 | L39: =IF(OR($E39<L$31,$D39>L$32),0,$C39*NETWORKDAYS(MAX($D39,L$31),MIN($E39,L$32),Feriados)/NETWORKDAYS($D39,$E39,Feriados)) -> 0
A40: 2.2 | B40: =INDEX(Tareas!$B$6:$B$37,MATCH(A40,Tareas!$A$6:$A$37,0)) -> Planos e inventario de espacios | C40: =SUMIF(Costos!$A$5:$A$88,A40,Costos!$I$5:$I$88) -> 2655 | D40: =INDEX(Tareas!$M$6:$M$37,MATCH(A40,Tareas!$A$6:$A$37,0)) -> 46323 | E40: =INDEX(Tareas!$N$6:$N$37,MATCH(A40,Tareas!$A$6:$A$37,0)) -> 46343 | F40: =IF(OR($E40<F$31,$D40>F$32),0,$C40*NETWORKDAYS(MAX($D40,F$31),MIN($E40,F$32),Feriados)/NETWORKDAYS($D40,$E40,Feriados)) -> 531 | G40: =IF(OR($E40<G$31,$D40>G$32),0,$C40*NETWORKDAYS(MAX($D40,G$31),MIN($E40,G$32),Feriados)/NETWORKDAYS($D40,$E40,Feriados)) -> 2124 | H40: =IF(OR($E40<H$31,$D40>H$32),0,$C40*NETWORKDAYS(MAX($D40,H$31),MIN($E40,H$32),Feriados)/NETWORKDAYS($D40,$E40,Feriados)) -> 0 | I40: =IF(OR($E40<I$31,$D40>I$32),0,$C40*NETWORKDAYS(MAX($D40,I$31),MIN($E40,I$32),Feriados)/NETWORKDAYS($D40,$E40,Feriados)) -> 0 | J40: =IF(OR($E40<J$31,$D40>J$32),0,$C40*NETWORKDAYS(MAX($D40,J$31),MIN($E40,J$32),Feriados)/NETWORKDAYS($D40,$E40,Feriados)) -> 0 | K40: =IF(OR($E40<K$31,$D40>K$32),0,$C40*NETWORKDAYS(MAX($D40,K$31),MIN($E40,K$32),Feriados)/NETWORKDAYS($D40,$E40,Feriados)) -> 0 | L40: =IF(OR($E40<L$31,$D40>L$32),0,$C40*NETWORKDAYS(MAX($D40,L$31),MIN($E40,L$32),Feriados)/NETWORKDAYS($D40,$E40,Feriados)) -> 0
A41: 2.3 | B41: =INDEX(Tareas!$B$6:$B$37,MATCH(A41,Tareas!$A$6:$A$37,0)) -> Módulo de reserva de escritorios | C41: =SUMIF(Costos!$A$5:$A$88,A41,Costos!$I$5:$I$88) -> 10728 | D41: =INDEX(Tareas!$M$6:$M$37,MATCH(A41,Tareas!$A$6:$A$37,0)) -> 46316 | E41: =INDEX(Tareas!$N$6:$N$37,MATCH(A41,Tareas!$A$6:$A$37,0)) -> 46339 | F41: =IF(OR($E41<F$31,$D41>F$32),0,$C41*NETWORKDAYS(MAX($D41,F$31),MIN($E41,F$32),Feriados)/NETWORKDAYS($D41,$E41,Feriados)) -> 4768 | G41: =IF(OR($E41<G$31,$D41>G$32),0,$C41*NETWORKDAYS(MAX($D41,G$31),MIN($E41,G$32),Feriados)/NETWORKDAYS($D41,$E41,Feriados)) -> 5960 | H41: =IF(OR($E41<H$31,$D41>H$32),0,$C41*NETWORKDAYS(MAX($D41,H$31),MIN($E41,H$32),Feriados)/NETWORKDAYS($D41,$E41,Feriados)) -> 0 | I41: =IF(OR($E41<I$31,$D41>I$32),0,$C41*NETWORKDAYS(MAX($D41,I$31),MIN($E41,I$32),Feriados)/NETWORKDAYS($D41,$E41,Feriados)) -> 0 | J41: =IF(OR($E41<J$31,$D41>J$32),0,$C41*NETWORKDAYS(MAX($D41,J$31),MIN($E41,J$32),Feriados)/NETWORKDAYS($D41,$E41,Feriados)) -> 0 | K41: =IF(OR($E41<K$31,$D41>K$32),0,$C41*NETWORKDAYS(MAX($D41,K$31),MIN($E41,K$32),Feriados)/NETWORKDAYS($D41,$E41,Feriados)) -> 0 | L41: =IF(OR($E41<L$31,$D41>L$32),0,$C41*NETWORKDAYS(MAX($D41,L$31),MIN($E41,L$32),Feriados)/NETWORKDAYS($D41,$E41,Feriados)) -> 0
A42: 2.4 | B42: =INDEX(Tareas!$B$6:$B$37,MATCH(A42,Tareas!$A$6:$A$37,0)) -> Módulo de reserva de salas | C42: =SUMIF(Costos!$A$5:$A$88,A42,Costos!$I$5:$I$88) -> 8940 | D42: =INDEX(Tareas!$M$6:$M$37,MATCH(A42,Tareas!$A$6:$A$37,0)) -> 46323 | E42: =INDEX(Tareas!$N$6:$N$37,MATCH(A42,Tareas!$A$6:$A$37,0)) -> 46343 | F42: =IF(OR($E42<F$31,$D42>F$32),0,$C42*NETWORKDAYS(MAX($D42,F$31),MIN($E42,F$32),Feriados)/NETWORKDAYS($D42,$E42,Feriados)) -> 1788 | G42: =IF(OR($E42<G$31,$D42>G$32),0,$C42*NETWORKDAYS(MAX($D42,G$31),MIN($E42,G$32),Feriados)/NETWORKDAYS($D42,$E42,Feriados)) -> 7152 | H42: =IF(OR($E42<H$31,$D42>H$32),0,$C42*NETWORKDAYS(MAX($D42,H$31),MIN($E42,H$32),Feriados)/NETWORKDAYS($D42,$E42,Feriados)) -> 0 | I42: =IF(OR($E42<I$31,$D42>I$32),0,$C42*NETWORKDAYS(MAX($D42,I$31),MIN($E42,I$32),Feriados)/NETWORKDAYS($D42,$E42,Feriados)) -> 0 | J42: =IF(OR($E42<J$31,$D42>J$32),0,$C42*NETWORKDAYS(MAX($D42,J$31),MIN($E42,J$32),Feriados)/NETWORKDAYS($D42,$E42,Feriados)) -> 0 | K42: =IF(OR($E42<K$31,$D42>K$32),0,$C42*NETWORKDAYS(MAX($D42,K$31),MIN($E42,K$32),Feriados)/NETWORKDAYS($D42,$E42,Feriados)) -> 0 | L42: =IF(OR($E42<L$31,$D42>L$32),0,$C42*NETWORKDAYS(MAX($D42,L$31),MIN($E42,L$32),Feriados)/NETWORKDAYS($D42,$E42,Feriados)) -> 0
A43: 2.5 | B43: =INDEX(Tareas!$B$6:$B$37,MATCH(A43,Tareas!$A$6:$A$37,0)) -> Check-in, check-out y liberación | C43: =SUMIF(Costos!$A$5:$A$88,A43,Costos!$I$5:$I$88) -> 6144 | D43: =INDEX(Tareas!$M$6:$M$37,MATCH(A43,Tareas!$A$6:$A$37,0)) -> 46342 | E43: =INDEX(Tareas!$N$6:$N$37,MATCH(A43,Tareas!$A$6:$A$37,0)) -> 46358 | F43: =IF(OR($E43<F$31,$D43>F$32),0,$C43*NETWORKDAYS(MAX($D43,F$31),MIN($E43,F$32),Feriados)/NETWORKDAYS($D43,$E43,Feriados)) -> 0 | G43: =IF(OR($E43<G$31,$D43>G$32),0,$C43*NETWORKDAYS(MAX($D43,G$31),MIN($E43,G$32),Feriados)/NETWORKDAYS($D43,$E43,Feriados)) -> 5120 | H43: =IF(OR($E43<H$31,$D43>H$32),0,$C43*NETWORKDAYS(MAX($D43,H$31),MIN($E43,H$32),Feriados)/NETWORKDAYS($D43,$E43,Feriados)) -> 1024 | I43: =IF(OR($E43<I$31,$D43>I$32),0,$C43*NETWORKDAYS(MAX($D43,I$31),MIN($E43,I$32),Feriados)/NETWORKDAYS($D43,$E43,Feriados)) -> 0 | J43: =IF(OR($E43<J$31,$D43>J$32),0,$C43*NETWORKDAYS(MAX($D43,J$31),MIN($E43,J$32),Feriados)/NETWORKDAYS($D43,$E43,Feriados)) -> 0 | K43: =IF(OR($E43<K$31,$D43>K$32),0,$C43*NETWORKDAYS(MAX($D43,K$31),MIN($E43,K$32),Feriados)/NETWORKDAYS($D43,$E43,Feriados)) -> 0 | L43: =IF(OR($E43<L$31,$D43>L$32),0,$C43*NETWORKDAYS(MAX($D43,L$31),MIN($E43,L$32),Feriados)/NETWORKDAYS($D43,$E43,Feriados)) -> 0
A44: 2.6 | B44: =INDEX(Tareas!$B$6:$B$37,MATCH(A44,Tareas!$A$6:$A$37,0)) -> Notificaciones y sugerencias | C44: =SUMIF(Costos!$A$5:$A$88,A44,Costos!$I$5:$I$88) -> 9120 | D44: =INDEX(Tareas!$M$6:$M$37,MATCH(A44,Tareas!$A$6:$A$37,0)) -> 46359 | E44: =INDEX(Tareas!$N$6:$N$37,MATCH(A44,Tareas!$A$6:$A$37,0)) -> 46384 | F44: =IF(OR($E44<F$31,$D44>F$32),0,$C44*NETWORKDAYS(MAX($D44,F$31),MIN($E44,F$32),Feriados)/NETWORKDAYS($D44,$E44,Feriados)) -> 0 | G44: =IF(OR($E44<G$31,$D44>G$32),0,$C44*NETWORKDAYS(MAX($D44,G$31),MIN($E44,G$32),Feriados)/NETWORKDAYS($D44,$E44,Feriados)) -> 0 | H44: =IF(OR($E44<H$31,$D44>H$32),0,$C44*NETWORKDAYS(MAX($D44,H$31),MIN($E44,H$32),Feriados)/NETWORKDAYS($D44,$E44,Feriados)) -> 9120 | I44: =IF(OR($E44<I$31,$D44>I$32),0,$C44*NETWORKDAYS(MAX($D44,I$31),MIN($E44,I$32),Feriados)/NETWORKDAYS($D44,$E44,Feriados)) -> 0 | J44: =IF(OR($E44<J$31,$D44>J$32),0,$C44*NETWORKDAYS(MAX($D44,J$31),MIN($E44,J$32),Feriados)/NETWORKDAYS($D44,$E44,Feriados)) -> 0 | K44: =IF(OR($E44<K$31,$D44>K$32),0,$C44*NETWORKDAYS(MAX($D44,K$31),MIN($E44,K$32),Feriados)/NETWORKDAYS($D44,$E44,Feriados)) -> 0 | L44: =IF(OR($E44<L$31,$D44>L$32),0,$C44*NETWORKDAYS(MAX($D44,L$31),MIN($E44,L$32),Feriados)/NETWORKDAYS($D44,$E44,Feriados)) -> 0
... A63: 5.6 | B63: =INDEX(Tareas!$B$6:$B$37,MATCH(A63,Tareas!$A$6:$A$37,0)) -> Informe de ocupación y recomendación | C63: =SUMIF(Costos!$A$5:$A$88,A63,Costos!$I$5:$I$88) -> 2690 | D63: =INDEX(Tareas!$M$6:$M$37,MATCH(A63,Tareas!$A$6:$A$37,0)) -> 46496 | E63: =INDEX(Tareas!$N$6:$N$37,MATCH(A63,Tareas!$A$6:$A$37,0)) -> 46507 | F63: =IF(OR($E63<F$31,$D63>F$32),0,$C63*NETWORKDAYS(MAX($D63,F$31),MIN($E63,F$32),Feriados)/NETWORKDAYS($D63,$E63,Feriados)) -> 0 | G63: =IF(OR($E63<G$31,$D63>G$32),0,$C63*NETWORKDAYS(MAX($D63,G$31),MIN($E63,G$32),Feriados)/NETWORKDAYS($D63,$E63,Feriados)) -> 0 | H63: =IF(OR($E63<H$31,$D63>H$32),0,$C63*NETWORKDAYS(MAX($D63,H$31),MIN($E63,H$32),Feriados)/NETWORKDAYS($D63,$E63,Feriados)) -> 0 | I63: =IF(OR($E63<I$31,$D63>I$32),0,$C63*NETWORKDAYS(MAX($D63,I$31),MIN($E63,I$32),Feriados)/NETWORKDAYS($D63,$E63,Feriados)) -> 0 | J63: =IF(OR($E63<J$31,$D63>J$32),0,$C63*NETWORKDAYS(MAX($D63,J$31),MIN($E63,J$32),Feriados)/NETWORKDAYS($D63,$E63,Feriados)) -> 0 | K63: =IF(OR($E63<K$31,$D63>K$32),0,$C63*NETWORKDAYS(MAX($D63,K$31),MIN($E63,K$32),Feriados)/NETWORKDAYS($D63,$E63,Feriados)) -> 0 | L63: =IF(OR($E63<L$31,$D63>L$32),0,$C63*NETWORKDAYS(MAX($D63,L$31),MIN($E63,L$32),Feriados)/NETWORKDAYS($D63,$E63,Feriados)) -> 2690
A64: P-1 | B64: =Partidas!B5 -> Licencia WorkHub, 1.200 usuarios nominados (primer año de soporte incluido) | C64: =Partidas!G5 -> 108000 | D64: =Partidas!J5 -> 46296 | E64: =Partidas!K5 -> 46296 | F64: =IF(OR($E64<F$31,$D64>F$32),0,$C64*NETWORKDAYS(MAX($D64,F$31),MIN($E64,F$32),Feriados)/NETWORKDAYS($D64,$E64,Feriados)) -> 108000 | G64: =IF(OR($E64<G$31,$D64>G$32),0,$C64*NETWORKDAYS(MAX($D64,G$31),MIN($E64,G$32),Feriados)/NETWORKDAYS($D64,$E64,Feriados)) -> 0 | H64: =IF(OR($E64<H$31,$D64>H$32),0,$C64*NETWORKDAYS(MAX($D64,H$31),MIN($E64,H$32),Feriados)/NETWORKDAYS($D64,$E64,Feriados)) -> 0 | I64: =IF(OR($E64<I$31,$D64>I$32),0,$C64*NETWORKDAYS(MAX($D64,I$31),MIN($E64,I$32),Feriados)/NETWORKDAYS($D64,$E64,Feriados)) -> 0 | J64: =IF(OR($E64<J$31,$D64>J$32),0,$C64*NETWORKDAYS(MAX($D64,J$31),MIN($E64,J$32),Feriados)/NETWORKDAYS($D64,$E64,Feriados)) -> 0 | K64: =IF(OR($E64<K$31,$D64>K$32),0,$C64*NETWORKDAYS(MAX($D64,K$31),MIN($E64,K$32),Feriados)/NETWORKDAYS($D64,$E64,Feriados)) -> 0 | L64: =IF(OR($E64<L$31,$D64>L$32),0,$C64*NETWORKDAYS(MAX($D64,L$31),MIN($E64,L$32),Feriados)/NETWORKDAYS($D64,$E64,Feriados)) -> 0
A65: P-2a | B65: =Partidas!B6 -> Entorno de desarrollo (Azure Brasil Sur) | C65: =Partidas!G6 -> 1050 | D65: =Partidas!J6 -> 46309 | E65: =Partidas!K6 -> 46507 | F65: =IF(OR($E65<F$31,$D65>F$32),0,$C65*NETWORKDAYS(MAX($D65,F$31),MIN($E65,F$32),Feriados)/NETWORKDAYS($D65,$E65,Feriados)) -> 103.40909 | G65: =IF(OR($E65<G$31,$D65>G$32),0,$C65*NETWORKDAYS(MAX($D65,G$31),MIN($E65,G$32),Feriados)/NETWORKDAYS($D65,$E65,Feriados)) -> 159.09091 | H65: =IF(OR($E65<H$31,$D65>H$32),0,$C65*NETWORKDAYS(MAX($D65,H$31),MIN($E65,H$32),Feriados)/NETWORKDAYS($D65,$E65,Feriados)) -> 159.09091 | I65: =IF(OR($E65<I$31,$D65>I$32),0,$C65*NETWORKDAYS(MAX($D65,I$31),MIN($E65,I$32),Feriados)/NETWORKDAYS($D65,$E65,Feriados)) -> 159.09091 | J65: =IF(OR($E65<J$31,$D65>J$32),0,$C65*NETWORKDAYS(MAX($D65,J$31),MIN($E65,J$32),Feriados)/NETWORKDAYS($D65,$E65,Feriados)) -> 143.18182 | K65: =IF(OR($E65<K$31,$D65>K$32),0,$C65*NETWORKDAYS(MAX($D65,K$31),MIN($E65,K$32),Feriados)/NETWORKDAYS($D65,$E65,Feriados)) -> 159.09091 | L65: =IF(OR($E65<L$31,$D65>L$32),0,$C65*NETWORKDAYS(MAX($D65,L$31),MIN($E65,L$32),Feriados)/NETWORKDAYS($D65,$E65,Feriados)) -> 167.04545
A66: P-2b | B66: =Partidas!B7 -> Entorno de QA / staging | C66: =Partidas!G7 -> 1500 | D66: =Partidas!J7 -> 46309 | E66: =Partidas!K7 -> 46505 | F66: =IF(OR($E66<F$31,$D66>F$32),0,$C66*NETWORKDAYS(MAX($D66,F$31),MIN($E66,F$32),Feriados)/NETWORKDAYS($D66,$E66,Feriados)) -> 150 | G66: =IF(OR($E66<G$31,$D66>G$32),0,$C66*NETWORKDAYS(MAX($D66,G$31),MIN($E66,G$32),Feriados)/NETWORKDAYS($D66,$E66,Feriados)) -> 230.76923 | H66: =IF(OR($E66<H$31,$D66>H$32),0,$C66*NETWORKDAYS(MAX($D66,H$31),MIN($E66,H$32),Feriados)/NETWORKDAYS($D66,$E66,Feriados)) -> 230.76923 | I66: =IF(OR($E66<I$31,$D66>I$32),0,$C66*NETWORKDAYS(MAX($D66,I$31),MIN($E66,I$32),Feriados)/NETWORKDAYS($D66,$E66,Feriados)) -> 230.76923 | J66: =IF(OR($E66<J$31,$D66>J$32),0,$C66*NETWORKDAYS(MAX($D66,J$31),MIN($E66,J$32),Feriados)/NETWORKDAYS($D66,$E66,Feriados)) -> 207.69231 | K66: =IF(OR($E66<K$31,$D66>K$32),0,$C66*NETWORKDAYS(MAX($D66,K$31),MIN($E66,K$32),Feriados)/NETWORKDAYS($D66,$E66,Feriados)) -> 230.76923 | L66: =IF(OR($E66<L$31,$D66>L$32),0,$C66*NETWORKDAYS(MAX($D66,L$31),MIN($E66,L$32),Feriados)/NETWORKDAYS($D66,$E66,Feriados)) -> 219.23077
A67: P-2c | B67: =Partidas!B8 -> Entorno de producción (alineado al hosting anual de N1: USD 5.060 / 12) | C67: =Partidas!G8 -> 844 | D67: =Partidas!J8 -> 46477 | E67: =Partidas!K8 -> 46507 | F67: =IF(OR($E67<F$31,$D67>F$32),0,$C67*NETWORKDAYS(MAX($D67,F$31),MIN($E67,F$32),Feriados)/NETWORKDAYS($D67,$E67,Feriados)) -> 0 | G67: =IF(OR($E67<G$31,$D67>G$32),0,$C67*NETWORKDAYS(MAX($D67,G$31),MIN($E67,G$32),Feriados)/NETWORKDAYS($D67,$E67,Feriados)) -> 0 | H67: =IF(OR($E67<H$31,$D67>H$32),0,$C67*NETWORKDAYS(MAX($D67,H$31),MIN($E67,H$32),Feriados)/NETWORKDAYS($D67,$E67,Feriados)) -> 0 | I67: =IF(OR($E67<I$31,$D67>I$32),0,$C67*NETWORKDAYS(MAX($D67,I$31),MIN($E67,I$32),Feriados)/NETWORKDAYS($D67,$E67,Feriados)) -> 0 | J67: =IF(OR($E67<J$31,$D67>J$32),0,$C67*NETWORKDAYS(MAX($D67,J$31),MIN($E67,J$32),Feriados)/NETWORKDAYS($D67,$E67,Feriados)) -> 0 | K67: =IF(OR($E67<K$31,$D67>K$32),0,$C67*NETWORKDAYS(MAX($D67,K$31),MIN($E67,K$32),Feriados)/NETWORKDAYS($D67,$E67,Feriados)) -> 38.363636 | L67: =IF(OR($E67<L$31,$D67>L$32),0,$C67*NETWORKDAYS(MAX($D67,L$31),MIN($E67,L$32),Feriados)/NETWORKDAYS($D67,$E67,Feriados)) -> 805.63636
A68: P-2d | B68: =Partidas!B9 -> Observabilidad y logs (APM) | C68: =Partidas!G9 -> 2100 | D68: =Partidas!J9 -> 46309 | E68: =Partidas!K9 -> 46507 | F68: =IF(OR($E68<F$31,$D68>F$32),0,$C68*NETWORKDAYS(MAX($D68,F$31),MIN($E68,F$32),Feriados)/NETWORKDAYS($D68,$E68,Feriados)) -> 206.81818 | G68: =IF(OR($E68<G$31,$D68>G$32),0,$C68*NETWORKDAYS(MAX($D68,G$31),MIN($E68,G$32),Feriados)/NETWORKDAYS($D68,$E68,Feriados)) -> 318.18182 | H68: =IF(OR($E68<H$31,$D68>H$32),0,$C68*NETWORKDAYS(MAX($D68,H$31),MIN($E68,H$32),Feriados)/NETWORKDAYS($D68,$E68,Feriados)) -> 318.18182 | I68: =IF(OR($E68<I$31,$D68>I$32),0,$C68*NETWORKDAYS(MAX($D68,I$31),MIN($E68,I$32),Feriados)/NETWORKDAYS($D68,$E68,Feriados)) -> 318.18182 | J68: =IF(OR($E68<J$31,$D68>J$32),0,$C68*NETWORKDAYS(MAX($D68,J$31),MIN($E68,J$32),Feriados)/NETWORKDAYS($D68,$E68,Feriados)) -> 286.36364 | K68: =IF(OR($E68<K$31,$D68>K$32),0,$C68*NETWORKDAYS(MAX($D68,K$31),MIN($E68,K$32),Feriados)/NETWORKDAYS($D68,$E68,Feriados)) -> 318.18182 | L68: =IF(OR($E68<L$31,$D68>L$32),0,$C68*NETWORKDAYS(MAX($D68,L$31),MIN($E68,L$32),Feriados)/NETWORKDAYS($D68,$E68,Feriados)) -> 334.09091
A69: P-2e | B69: =Partidas!B10 -> Herramientas de soporte del equipo (CI/CD, backlog, bóveda de secretos) | C69: =Partidas!G10 -> 1680 | D69: =Partidas!J10 -> 46309 | E69: =Partidas!K10 -> 46507 | F69: =IF(OR($E69<F$31,$D69>F$32),0,$C69*NETWORKDAYS(MAX($D69,F$31),MIN($E69,F$32),Feriados)/NETWORKDAYS($D69,$E69,Feriados)) -> 165.45455 | G69: =IF(OR($E69<G$31,$D69>G$32),0,$C69*NETWORKDAYS(MAX($D69,G$31),MIN($E69,G$32),Feriados)/NETWORKDAYS($D69,$E69,Feriados)) -> 254.54545 | H69: =IF(OR($E69<H$31,$D69>H$32),0,$C69*NETWORKDAYS(MAX($D69,H$31),MIN($E69,H$32),Feriados)/NETWORKDAYS($D69,$E69,Feriados)) -> 254.54545 | I69: =IF(OR($E69<I$31,$D69>I$32),0,$C69*NETWORKDAYS(MAX($D69,I$31),MIN($E69,I$32),Feriados)/NETWORKDAYS($D69,$E69,Feriados)) -> 254.54545 | J69: =IF(OR($E69<J$31,$D69>J$32),0,$C69*NETWORKDAYS(MAX($D69,J$31),MIN($E69,J$32),Feriados)/NETWORKDAYS($D69,$E69,Feriados)) -> 229.09091 | K69: =IF(OR($E69<K$31,$D69>K$32),0,$C69*NETWORKDAYS(MAX($D69,K$31),MIN($E69,K$32),Feriados)/NETWORKDAYS($D69,$E69,Feriados)) -> 254.54545 | L69: =IF(OR($E69<L$31,$D69>L$32),0,$C69*NETWORKDAYS(MAX($D69,L$31),MIN($E69,L$32),Feriados)/NETWORKDAYS($D69,$E69,Feriados)) -> 267.27273
A70: P-3a | B70: =Partidas!B11 -> Piezas de la campaña de lanzamiento (diseño y producción) | C70: =Partidas!G11 -> 3600 | D70: =Partidas!J11 -> 46447 | E70: =Partidas!K11 -> 46465 | F70: =IF(OR($E70<F$31,$D70>F$32),0,$C70*NETWORKDAYS(MAX($D70,F$31),MIN($E70,F$32),Feriados)/NETWORKDAYS($D70,$E70,Feriados)) -> 0 | G70: =IF(OR($E70<G$31,$D70>G$32),0,$C70*NETWORKDAYS(MAX($D70,G$31),MIN($E70,G$32),Feriados)/NETWORKDAYS($D70,$E70,Feriados)) -> 0 | H70: =IF(OR($E70<H$31,$D70>H$32),0,$C70*NETWORKDAYS(MAX($D70,H$31),MIN($E70,H$32),Feriados)/NETWORKDAYS($D70,$E70,Feriados)) -> 0 | I70: =IF(OR($E70<I$31,$D70>I$32),0,$C70*NETWORKDAYS(MAX($D70,I$31),MIN($E70,I$32),Feriados)/NETWORKDAYS($D70,$E70,Feriados)) -> 0 | J70: =IF(OR($E70<J$31,$D70>J$32),0,$C70*NETWORKDAYS(MAX($D70,J$31),MIN($E70,J$32),Feriados)/NETWORKDAYS($D70,$E70,Feriados)) -> 0 | K70: =IF(OR($E70<K$31,$D70>K$32),0,$C70*NETWORKDAYS(MAX($D70,K$31),MIN($E70,K$32),Feriados)/NETWORKDAYS($D70,$E70,Feriados)) -> 3600 | L70: =IF(OR($E70<L$31,$D70>L$32),0,$C70*NETWORKDAYS(MAX($D70,L$31),MIN($E70,L$32),Feriados)/NETWORKDAYS($D70,$E70,Feriados)) -> 0
A71: P-3b | B71: =Partidas!B12 -> Materiales de capacitación (video-tutoriales y guías) | C71: =Partidas!G12 -> 3600 | D71: =Partidas!J12 -> 46336 | E71: =Partidas!K12 -> 46373 | F71: =IF(OR($E71<F$31,$D71>F$32),0,$C71*NETWORKDAYS(MAX($D71,F$31),MIN($E71,F$32),Feriados)/NETWORKDAYS($D71,$E71,Feriados)) -> 0 | G71: =IF(OR($E71<G$31,$D71>G$32),0,$C71*NETWORKDAYS(MAX($D71,G$31),MIN($E71,G$32),Feriados)/NETWORKDAYS($D71,$E71,Feriados)) -> 2016 | H71: =IF(OR($E71<H$31,$D71>H$32),0,$C71*NETWORKDAYS(MAX($D71,H$31),MIN($E71,H$32),Feriados)/NETWORKDAYS($D71,$E71,Feriados)) -> 1584 | I71: =IF(OR($E71<I$31,$D71>I$32),0,$C71*NETWORKDAYS(MAX($D71,I$31),MIN($E71,I$32),Feriados)/NETWORKDAYS($D71,$E71,Feriados)) -> 0 | J71: =IF(OR($E71<J$31,$D71>J$32),0,$C71*NETWORKDAYS(MAX($D71,J$31),MIN($E71,J$32),Feriados)/NETWORKDAYS($D71,$E71,Feriados)) -> 0 | K71: =IF(OR($E71<K$31,$D71>K$32),0,$C71*NETWORKDAYS(MAX($D71,K$31),MIN($E71,K$32),Feriados)/NETWORKDAYS($D71,$E71,Feriados)) -> 0 | L71: =IF(OR($E71<L$31,$D71>L$32),0,$C71*NETWORKDAYS(MAX($D71,L$31),MIN($E71,L$32),Feriados)/NETWORKDAYS($D71,$E71,Feriados)) -> 0
A72: P-3c | B72: =Partidas!B13 -> Sesiones de capacitación a 1.200 colaboradores (logística) | C72: =Partidas!G13 -> 3600 | D72: =Partidas!J13 -> 46336 | E72: =Partidas!K13 -> 46373 | F72: =IF(OR($E72<F$31,$D72>F$32),0,$C72*NETWORKDAYS(MAX($D72,F$31),MIN($E72,F$32),Feriados)/NETWORKDAYS($D72,$E72,Feriados)) -> 0 | G72: =IF(OR($E72<G$31,$D72>G$32),0,$C72*NETWORKDAYS(MAX($D72,G$31),MIN($E72,G$32),Feriados)/NETWORKDAYS($D72,$E72,Feriados)) -> 2016 | H72: =IF(OR($E72<H$31,$D72>H$32),0,$C72*NETWORKDAYS(MAX($D72,H$31),MIN($E72,H$32),Feriados)/NETWORKDAYS($D72,$E72,Feriados)) -> 1584 | I72: =IF(OR($E72<I$31,$D72>I$32),0,$C72*NETWORKDAYS(MAX($D72,I$31),MIN($E72,I$32),Feriados)/NETWORKDAYS($D72,$E72,Feriados)) -> 0 | J72: =IF(OR($E72<J$31,$D72>J$32),0,$C72*NETWORKDAYS(MAX($D72,J$31),MIN($E72,J$32),Feriados)/NETWORKDAYS($D72,$E72,Feriados)) -> 0 | K72: =IF(OR($E72<K$31,$D72>K$32),0,$C72*NETWORKDAYS(MAX($D72,K$31),MIN($E72,K$32),Feriados)/NETWORKDAYS($D72,$E72,Feriados)) -> 0 | L72: =IF(OR($E72<L$31,$D72>L$32),0,$C72*NETWORKDAYS(MAX($D72,L$31),MIN($E72,L$32),Feriados)/NETWORKDAYS($D72,$E72,Feriados)) -> 0
A73: P-3d | B73: =Partidas!B14 -> Encuestas de intención de uso y pulso | C73: =Partidas!G14 -> 900 | D73: =Partidas!J14 -> 46308 | E73: =Partidas!K14 -> 46321 | F73: =IF(OR($E73<F$31,$D73>F$32),0,$C73*NETWORKDAYS(MAX($D73,F$31),MIN($E73,F$32),Feriados)/NETWORKDAYS($D73,$E73,Feriados)) -> 900 | G73: =IF(OR($E73<G$31,$D73>G$32),0,$C73*NETWORKDAYS(MAX($D73,G$31),MIN($E73,G$32),Feriados)/NETWORKDAYS($D73,$E73,Feriados)) -> 0 | H73: =IF(OR($E73<H$31,$D73>H$32),0,$C73*NETWORKDAYS(MAX($D73,H$31),MIN($E73,H$32),Feriados)/NETWORKDAYS($D73,$E73,Feriados)) -> 0 | I73: =IF(OR($E73<I$31,$D73>I$32),0,$C73*NETWORKDAYS(MAX($D73,I$31),MIN($E73,I$32),Feriados)/NETWORKDAYS($D73,$E73,Feriados)) -> 0 | J73: =IF(OR($E73<J$31,$D73>J$32),0,$C73*NETWORKDAYS(MAX($D73,J$31),MIN($E73,J$32),Feriados)/NETWORKDAYS($D73,$E73,Feriados)) -> 0 | K73: =IF(OR($E73<K$31,$D73>K$32),0,$C73*NETWORKDAYS(MAX($D73,K$31),MIN($E73,K$32),Feriados)/NETWORKDAYS($D73,$E73,Feriados)) -> 0 | L73: =IF(OR($E73<L$31,$D73>L$32),0,$C73*NETWORKDAYS(MAX($D73,L$31),MIN($E73,L$32),Feriados)/NETWORKDAYS($D73,$E73,Feriados)) -> 0
A74: P-4a | B74: =Partidas!B15 -> Prueba de intrusión externa (requisito RA-2) | C74: =Partidas!G15 -> 7500 | D74: =Partidas!J15 -> 46339 | E74: =Partidas!K15 -> 46360 | F74: =IF(OR($E74<F$31,$D74>F$32),0,$C74*NETWORKDAYS(MAX($D74,F$31),MIN($E74,F$32),Feriados)/NETWORKDAYS($D74,$E74,Feriados)) -> 0 | G74: =IF(OR($E74<G$31,$D74>G$32),0,$C74*NETWORKDAYS(MAX($D74,G$31),MIN($E74,G$32),Feriados)/NETWORKDAYS($D74,$E74,Feriados)) -> 5500 | H74: =IF(OR($E74<H$31,$D74>H$32),0,$C74*NETWORKDAYS(MAX($D74,H$31),MIN($E74,H$32),Feriados)/NETWORKDAYS($D74,$E74,Feriados)) -> 2000 | I74: =IF(OR($E74<I$31,$D74>I$32),0,$C74*NETWORKDAYS(MAX($D74,I$31),MIN($E74,I$32),Feriados)/NETWORKDAYS($D74,$E74,Feriados)) -> 0 | J74: =IF(OR($E74<J$31,$D74>J$32),0,$C74*NETWORKDAYS(MAX($D74,J$31),MIN($E74,J$32),Feriados)/NETWORKDAYS($D74,$E74,Feriados)) -> 0 | K74: =IF(OR($E74<K$31,$D74>K$32),0,$C74*NETWORKDAYS(MAX($D74,K$31),MIN($E74,K$32),Feriados)/NETWORKDAYS($D74,$E74,Feriados)) -> 0 | L74: =IF(OR($E74<L$31,$D74>L$32),0,$C74*NETWORKDAYS(MAX($D74,L$31),MIN($E74,L$32),Feriados)/NETWORKDAYS($D74,$E74,Feriados)) -> 0
A75: P-4b | B75: =Partidas!B16 -> Entornos sandbox de conectores (HRIS y Exchange) | C75: =Partidas!G16 -> 2400 | D75: =Partidas!J16 -> 46309 | E75: =Partidas!K16 -> 46338 | F75: =IF(OR($E75<F$31,$D75>F$32),0,$C75*NETWORKDAYS(MAX($D75,F$31),MIN($E75,F$32),Feriados)/NETWORKDAYS($D75,$E75,Feriados)) -> 1418.1818 | G75: =IF(OR($E75<G$31,$D75>G$32),0,$C75*NETWORKDAYS(MAX($D75,G$31),MIN($E75,G$32),Feriados)/NETWORKDAYS($D75,$E75,Feriados)) -> 981.81818 | H75: =IF(OR($E75<H$31,$D75>H$32),0,$C75*NETWORKDAYS(MAX($D75,H$31),MIN($E75,H$32),Feriados)/NETWORKDAYS($D75,$E75,Feriados)) -> 0 | I75: =IF(OR($E75<I$31,$D75>I$32),0,$C75*NETWORKDAYS(MAX($D75,I$31),MIN($E75,I$32),Feriados)/NETWORKDAYS($D75,$E75,Feriados)) -> 0 | J75: =IF(OR($E75<J$31,$D75>J$32),0,$C75*NETWORKDAYS(MAX($D75,J$31),MIN($E75,J$32),Feriados)/NETWORKDAYS($D75,$E75,Feriados)) -> 0 | K75: =IF(OR($E75<K$31,$D75>K$32),0,$C75*NETWORKDAYS(MAX($D75,K$31),MIN($E75,K$32),Feriados)/NETWORKDAYS($D75,$E75,Feriados)) -> 0 | L75: =IF(OR($E75<L$31,$D75>L$32),0,$C75*NETWORKDAYS(MAX($D75,L$31),MIN($E75,L$32),Feriados)/NETWORKDAYS($D75,$E75,Feriados)) -> 0
B76: Total actividades | C76: =SUM(C33:C75) -> 372700 | F76: =SUM(F33:F75) -> 158853.86 | G76: =SUM(G33:G75) -> 75859.406 | H76: =SUM(H33:H75) -> 47604.587 | I76: =SUM(I33:I75) -> 14688.587 | J76: =SUM(J33:J75) -> 5546.3287 | K76: =SUM(K33:K75) -> 26162.951 | L76: =SUM(L33:L75) -> 43984.276
B77: Contingencia prorrateada (según gasto mensual) | C77: =Contingencia -> 22000 | F77: =Contingencia*F76/$C$76 -> 9376.9386 | G77: =Contingencia*G76/$C$76 -> 4477.8828 | H77: =Contingencia*H76/$C$76 -> 2810.0374 | I77: =Contingencia*I76/$C$76 -> 867.04836 | J77: =Contingencia*J76/$C$76 -> 327.39262 | K77: =Contingencia*K76/$C$76 -> 1544.3652 | L77: =Contingencia*L76/$C$76 -> 2596.3351
B78: Línea base mensual | C78: =C76+C77 -> 394700 | F78: =F76+F77 -> 168230.8 | G78: =G76+G77 -> 80337.288 | H78: =H76+H77 -> 50414.625 | I78: =I76+I77 -> 15555.636 | J78: =J76+J77 -> 5873.7213 | K78: =K76+K77 -> 27707.316 | L78: =L76+L77 -> 46580.611
B79: Línea base acumulada | F79: =F78 -> 168230.8 | G79: =F79+G78 -> 248568.09 | H79: =G79+H78 -> 298982.72 | I79: =H79+I78 -> 314538.35 | J79: =I79+J78 -> 320412.07 | K79: =J79+K78 -> 348119.39 | L79: =K79+L78 -> 394700
B80: Avance acumulado (%) | F80: =F79/$B$20 -> 0.42622448 | G80: =G79/$B$20 -> 0.62976461 | H80: =H79/$B$20 -> 0.75749358 | I80: =I79/$B$20 -> 0.79690487 | J80: =J79/$B$20 -> 0.81178635 | K80: =K79/$B$20 -> 0.88198477 | L80: =L79/$B$20 -> 1
B81: Control: distribución mensual = línea base | C81: =IF(ABS(SUM(F78:L78)-B20)<1,"OK","REVISAR") -> OK
B82: Control: costo por tarea + partidas = costo base ascendente | C82: =IF(ABS(C76-B18)<1,"OK","REVISAR") -> OK
B84: La licencia (P-1) se paga a la firma, por eso el primer mes concentra buena parte de la línea base. La contingencia se prorratea según el gasto mensual (simplificación).

Sheet Curva S
A1: Curva S de la línea base de costos
A3: Mes | B3: Línea base mensual | C3: Línea base acumulada | D3: Avance acumulado
A4: 46296 | B4: =Presupuesto!F78 -> 168230.8 | C4: =Presupuesto!F79 -> 168230.8 | D4: =Presupuesto!F80 -> 0.42622448
A5: 46327 | B5: =Presupuesto!G78 -> 80337.288 | C5: =Presupuesto!G79 -> 248568.09 | D5: =Presupuesto!G80 -> 0.62976461
A6: 46357 | B6: =Presupuesto!H78 -> 50414.625 | C6: =Presupuesto!H79 -> 298982.72 | D6: =Presupuesto!H80 -> 0.75749358
A7: 46388 | B7: =Presupuesto!I78 -> 15555.636 | C7: =Presupuesto!I79 -> 314538.35 | D7: =Presupuesto!I80 -> 0.79690487
A8: 46419 | B8: =Presupuesto!J78 -> 5873.7213 | C8: =Presupuesto!J79 -> 320412.07 | D8: =Presupuesto!J80 -> 0.81178635
A9: 46447 | B9: =Presupuesto!K78 -> 27707.316 | C9: =Presupuesto!K79 -> 348119.39 | D9: =Presupuesto!K80 -> 0.88198477
A10: 46478 | B10: =Presupuesto!L78 -> 46580.611 | C10: =Presupuesto!L79 -> 394700 | D10: =Presupuesto!L80 -> 1

Sheet Carga de recursos
A1: Carga diaria de cada recurso frente a su capacidad
A2: Suma de las unidades asignadas a las tareas activas cada día hábil. Debe ser ≤ capacidad: así se verifica con qué recursos se ejecuta el plan sin sobreasignar a nadie.
A3: Capacidad (FTE) | C3: =INDEX(Recursos!$E$5:$E$16,MATCH(C$4,Recursos!$A$5:$A$16,0)) -> 1 | D3: =INDEX(Recursos!$E$5:$E$16,MATCH(D$4,Recursos!$A$5:$A$16,0)) -> 1 | E3: =INDEX(Recursos!$E$5:$E$16,MATCH(E$4,Recursos!$A$5:$A$16,0)) -> 1 | F3: =INDEX(Recursos!$E$5:$E$16,MATCH(F$4,Recursos!$A$5:$A$16,0)) -> 2 | G3: =INDEX(Recursos!$E$5:$E$16,MATCH(G$4,Recursos!$A$5:$A$16,0)) -> 1 | H3: =INDEX(Recursos!$E$5:$E$16,MATCH(H$4,Recursos!$A$5:$A$16,0)) -> 2 | I3: =INDEX(Recursos!$E$5:$E$16,MATCH(I$4,Recursos!$A$5:$A$16,0)) -> 1 | J3: =INDEX(Recursos!$E$5:$E$16,MATCH(J$4,Recursos!$A$5:$A$16,0)) -> 1 | ... N3: =INDEX(Recursos!$E$5:$E$16,MATCH(N$4,Recursos!$A$5:$A$16,0)) -> 99
A4: Índice | B4: Fecha | C4: PM | D4: PO | E4: UX | F4: DEV | G4: QA | H4: INT | I4: OPS | J4: CAM | K4: TEC | L4: SG | M4: RH | N4: USR
A5: 0 | B5: =INDEX(Calendario!$B$3:$B$172,A5+1) -> 46296 | C5: =SUMPRODUCT((Costos!$C$5:$C$88=C$4)*Costos!$E$5:$E$88*(Costos!$K$5:$K$88<=$A5)*(Costos!$L$5:$L$88>$A5)) -> 1 | D5: =SUMPRODUCT((Costos!$C$5:$C$88=D$4)*Costos!$E$5:$E$88*(Costos!$K$5:$K$88<=$A5)*(Costos!$L$5:$L$88>$A5)) -> 0 | E5: =SUMPRODUCT((Costos!$C$5:$C$88=E$4)*Costos!$E$5:$E$88*(Costos!$K$5:$K$88<=$A5)*(Costos!$L$5:$L$88>$A5)) -> 0 | F5: =SUMPRODUCT((Costos!$C$5:$C$88=F$4)*Costos!$E$5:$E$88*(Costos!$K$5:$K$88<=$A5)*(Costos!$L$5:$L$88>$A5)) -> 0 | G5: =SUMPRODUCT((Costos!$C$5:$C$88=G$4)*Costos!$E$5:$E$88*(Costos!$K$5:$K$88<=$A5)*(Costos!$L$5:$L$88>$A5)) -> 0 | H5: =SUMPRODUCT((Costos!$C$5:$C$88=H$4)*Costos!$E$5:$E$88*(Costos!$K$5:$K$88<=$A5)*(Costos!$L$5:$L$88>$A5)) -> 0 | I5: =SUMPRODUCT((Costos!$C$5:$C$88=I$4)*Costos!$E$5:$E$88*(Costos!$K$5:$K$88<=$A5)*(Costos!$L$5:$L$88>$A5)) -> 0 | J5: =SUMPRODUCT((Costos!$C$5:$C$88=J$4)*Costos!$E$5:$E$88*(Costos!$K$5:$K$88<=$A5)*(Costos!$L$5:$L$88>$A5)) -> 0 | ... N5: =SUMPRODUCT((Costos!$C$5:$C$88=N$4)*Costos!$E$5:$E$88*(Costos!$K$5:$K$88<=$A5)*(Costos!$L$5:$L$88>$A5)) -> 0
A6: 1 | B6: =INDEX(Calendario!$B$3:$B$172,A6+1) -> 46297 | C6: =SUMPRODUCT((Costos!$C$5:$C$88=C$4)*Costos!$E$5:$E$88*(Costos!$K$5:$K$88<=$A6)*(Costos!$L$5:$L$88>$A6)) -> 1 | D6: =SUMPRODUCT((Costos!$C$5:$C$88=D$4)*Costos!$E$5:$E$88*(Costos!$K$5:$K$88<=$A6)*(Costos!$L$5:$L$88>$A6)) -> 0 | E6: =SUMPRODUCT((Costos!$C$5:$C$88=E$4)*Costos!$E$5:$E$88*(Costos!$K$5:$K$88<=$A6)*(Costos!$L$5:$L$88>$A6)) -> 0 | F6: =SUMPRODUCT((Costos!$C$5:$C$88=F$4)*Costos!$E$5:$E$88*(Costos!$K$5:$K$88<=$A6)*(Costos!$L$5:$L$88>$A6)) -> 0 | G6: =SUMPRODUCT((Costos!$C$5:$C$88=G$4)*Costos!$E$5:$E$88*(Costos!$K$5:$K$88<=$A6)*(Costos!$L$5:$L$88>$A6)) -> 0 | H6: =SUMPRODUCT((Costos!$C$5:$C$88=H$4)*Costos!$E$5:$E$88*(Costos!$K$5:$K$88<=$A6)*(Costos!$L$5:$L$88>$A6)) -> 0 | I6: =SUMPRODUCT((Costos!$C$5:$C$88=I$4)*Costos!$E$5:$E$88*(Costos!$K$5:$K$88<=$A6)*(Costos!$L$5:$L$88>$A6)) -> 0 | J6: =SUMPRODUCT((Costos!$C$5:$C$88=J$4)*Costos!$E$5:$E$88*(Costos!$K$5:$K$88<=$A6)*(Costos!$L$5:$L$88>$A6)) -> 0 | ... N6: =SUMPRODUCT((Costos!$C$5:$C$88=N$4)*Costos!$E$5:$E$88*(Costos!$K$5:$K$88<=$A6)*(Costos!$L$5:$L$88>$A6)) -> 0
A7: 2 | B7: =INDEX(Calendario!$B$3:$B$172,A7+1) -> 46300 | C7: =SUMPRODUCT((Costos!$C$5:$C$88=C$4)*Costos!$E$5:$E$88*(Costos!$K$5:$K$88<=$A7)*(Costos!$L$5:$L$88>$A7)) -> 1 | D7: =SUMPRODUCT((Costos!$C$5:$C$88=D$4)*Costos!$E$5:$E$88*(Costos!$K$5:$K$88<=$A7)*(Costos!$L$5:$L$88>$A7)) -> 0.2 | E7: =SUMPRODUCT((Costos!$C$5:$C$88=E$4)*Costos!$E$5:$E$88*(Costos!$K$5:$K$88<=$A7)*(Costos!$L$5:$L$88>$A7)) -> 0 | F7: =SUMPRODUCT((Costos!$C$5:$C$88=F$4)*Costos!$E$5:$E$88*(Costos!$K$5:$K$88<=$A7)*(Costos!$L$5:$L$88>$A7)) -> 0 | G7: =SUMPRODUCT((Costos!$C$5:$C$88=G$4)*Costos!$E$5:$E$88*(Costos!$K$5:$K$88<=$A7)*(Costos!$L$5:$L$88>$A7)) -> 0 | H7: =SUMPRODUCT((Costos!$C$5:$C$88=H$4)*Costos!$E$5:$E$88*(Costos!$K$5:$K$88<=$A7)*(Costos!$L$5:$L$88>$A7)) -> 0 | I7: =SUMPRODUCT((Costos!$C$5:$C$88=I$4)*Costos!$E$5:$E$88*(Costos!$K$5:$K$88<=$A7)*(Costos!$L$5:$L$88>$A7)) -> 0 | J7: =SUMPRODUCT((Costos!$C$5:$C$88=J$4)*Costos!$E$5:$E$88*(Costos!$K$5:$K$88<=$A7)*(Costos!$L$5:$L$88>$A7)) -> 0 | ... N7: =SUMPRODUCT((Costos!$C$5:$C$88=N$4)*Costos!$E$5:$E$88*(Costos!$K$5:$K$88<=$A7)*(Costos!$L$5:$L$88>$A7)) -> 0
A8: 3 | B8: =INDEX(Calendario!$B$3:$B$172,A8+1) -> 46301 | C8: =SUMPRODUCT((Costos!$C$5:$C$88=C$4)*Costos!$E$5:$E$88*(Costos!$K$5:$K$88<=$A8)*(Costos!$L$5:$L$88>$A8)) -> 1 | D8: =SUMPRODUCT((Costos!$C$5:$C$88=D$4)*Costos!$E$5:$E$88*(Costos!$K$5:$K$88<=$A8)*(Costos!$L$5:$L$88>$A8)) -> 0.2 | E8: =SUMPRODUCT((Costos!$C$5:$C$88=E$4)*Costos!$E$5:$E$88*(Costos!$K$5:$K$88<=$A8)*(Costos!$L$5:$L$88>$A8)) -> 0 | F8: =SUMPRODUCT((Costos!$C$5:$C$88=F$4)*Costos!$E$5:$E$88*(Costos!$K$5:$K$88<=$A8)*(Costos!$L$5:$L$88>$A8)) -> 0 | G8: =SUMPRODUCT((Costos!$C$5:$C$88=G$4)*Costos!$E$5:$E$88*(Costos!$K$5:$K$88<=$A8)*(Costos!$L$5:$L$88>$A8)) -> 0 | H8: =SUMPRODUCT((Costos!$C$5:$C$88=H$4)*Costos!$E$5:$E$88*(Costos!$K$5:$K$88<=$A8)*(Costos!$L$5:$L$88>$A8)) -> 0 | I8: =SUMPRODUCT((Costos!$C$5:$C$88=I$4)*Costos!$E$5:$E$88*(Costos!$K$5:$K$88<=$A8)*(Costos!$L$5:$L$88>$A8)) -> 0 | J8: =SUMPRODUCT((Costos!$C$5:$C$88=J$4)*Costos!$E$5:$E$88*(Costos!$K$5:$K$88<=$A8)*(Costos!$L$5:$L$88>$A8)) -> 0 | ... N8: =SUMPRODUCT((Costos!$C$5:$C$88=N$4)*Costos!$E$5:$E$88*(Costos!$K$5:$K$88<=$A8)*(Costos!$L$5:$L$88>$A8)) -> 0
A9: 4 | B9: =INDEX(Calendario!$B$3:$B$172,A9+1) -> 46302 | C9: =SUMPRODUCT((Costos!$C$5:$C$88=C$4)*Costos!$E$5:$E$88*(Costos!$K$5:$K$88<=$A9)*(Costos!$L$5:$L$88>$A9)) -> 1 | D9: =SUMPRODUCT((Costos!$C$5:$C$88=D$4)*Costos!$E$5:$E$88*(Costos!$K$5:$K$88<=$A9)*(Costos!$L$5:$L$88>$A9)) -> 0.2 | E9: =SUMPRODUCT((Costos!$C$5:$C$88=E$4)*Costos!$E$5:$E$88*(Costos!$K$5:$K$88<=$A9)*(Costos!$L$5:$L$88>$A9)) -> 0 | F9: =SUMPRODUCT((Costos!$C$5:$C$88=F$4)*Costos!$E$5:$E$88*(Costos!$K$5:$K$88<=$A9)*(Costos!$L$5:$L$88>$A9)) -> 0 | G9: =SUMPRODUCT((Costos!$C$5:$C$88=G$4)*Costos!$E$5:$E$88*(Costos!$K$5:$K$88<=$A9)*(Costos!$L$5:$L$88>$A9)) -> 0 | H9: =SUMPRODUCT((Costos!$C$5:$C$88=H$4)*Costos!$E$5:$E$88*(Costos!$K$5:$K$88<=$A9)*(Costos!$L$5:$L$88>$A9)) -> 0 | I9: =SUMPRODUCT((Costos!$C$5:$C$88=I$4)*Costos!$E$5:$E$88*(Costos!$K$5:$K$88<=$A9)*(Costos!$L$5:$L$88>$A9)) -> 0 | J9: =SUMPRODUCT((Costos!$C$5:$C$88=J$4)*Costos!$E$5:$E$88*(Costos!$K$5:$K$88<=$A9)*(Costos!$L$5:$L$88>$A9)) -> 0 | ... N9: =SUMPRODUCT((Costos!$C$5:$C$88=N$4)*Costos!$E$5:$E$88*(Costos!$K$5:$K$88<=$A9)*(Costos!$L$5:$L$88>$A9)) -> 0
A10: 5 | B10: =INDEX(Calendario!$B$3:$B$172,A10+1) -> 46303 | C10: =SUMPRODUCT((Costos!$C$5:$C$88=C$4)*Costos!$E$5:$E$88*(Costos!$K$5:$K$88<=$A10)*(Costos!$L$5:$L$88>$A10)) -> 1 | D10: =SUMPRODUCT((Costos!$C$5:$C$88=D$4)*Costos!$E$5:$E$88*(Costos!$K$5:$K$88<=$A10)*(Costos!$L$5:$L$88>$A10)) -> 0.2 | E10: =SUMPRODUCT((Costos!$C$5:$C$88=E$4)*Costos!$E$5:$E$88*(Costos!$K$5:$K$88<=$A10)*(Costos!$L$5:$L$88>$A10)) -> 0 | F10: =SUMPRODUCT((Costos!$C$5:$C$88=F$4)*Costos!$E$5:$E$88*(Costos!$K$5:$K$88<=$A10)*(Costos!$L$5:$L$88>$A10)) -> 0 | G10: =SUMPRODUCT((Costos!$C$5:$C$88=G$4)*Costos!$E$5:$E$88*(Costos!$K$5:$K$88<=$A10)*(Costos!$L$5:$L$88>$A10)) -> 0 | H10: =SUMPRODUCT((Costos!$C$5:$C$88=H$4)*Costos!$E$5:$E$88*(Costos!$K$5:$K$88<=$A10)*(Costos!$L$5:$L$88>$A10)) -> 0 | I10: =SUMPRODUCT((Costos!$C$5:$C$88=I$4)*Costos!$E$5:$E$88*(Costos!$K$5:$K$88<=$A10)*(Costos!$L$5:$L$88>$A10)) -> 0 | J10: =SUMPRODUCT((Costos!$C$5:$C$88=J$4)*Costos!$E$5:$E$88*(Costos!$K$5:$K$88<=$A10)*(Costos!$L$5:$L$88>$A10)) -> 0 | ... N10: =SUMPRODUCT((Costos!$C$5:$C$88=N$4)*Costos!$E$5:$E$88*(Costos!$K$5:$K$88<=$A10)*(Costos!$L$5:$L$88>$A10)) -> 0
A11: 6 | B11: =INDEX(Calendario!$B$3:$B$172,A11+1) -> 46304 | C11: =SUMPRODUCT((Costos!$C$5:$C$88=C$4)*Costos!$E$5:$E$88*(Costos!$K$5:$K$88<=$A11)*(Costos!$L$5:$L$88>$A11)) -> 1 | D11: =SUMPRODUCT((Costos!$C$5:$C$88=D$4)*Costos!$E$5:$E$88*(Costos!$K$5:$K$88<=$A11)*(Costos!$L$5:$L$88>$A11)) -> 0.2 | E11: =SUMPRODUCT((Costos!$C$5:$C$88=E$4)*Costos!$E$5:$E$88*(Costos!$K$5:$K$88<=$A11)*(Costos!$L$5:$L$88>$A11)) -> 0 | F11: =SUMPRODUCT((Costos!$C$5:$C$88=F$4)*Costos!$E$5:$E$88*(Costos!$K$5:$K$88<=$A11)*(Costos!$L$5:$L$88>$A11)) -> 0 | G11: =SUMPRODUCT((Costos!$C$5:$C$88=G$4)*Costos!$E$5:$E$88*(Costos!$K$5:$K$88<=$A11)*(Costos!$L$5:$L$88>$A11)) -> 0 | H11: =SUMPRODUCT((Costos!$C$5:$C$88=H$4)*Costos!$E$5:$E$88*(Costos!$K$5:$K$88<=$A11)*(Costos!$L$5:$L$88>$A11)) -> 0 | I11: =SUMPRODUCT((Costos!$C$5:$C$88=I$4)*Costos!$E$5:$E$88*(Costos!$K$5:$K$88<=$A11)*(Costos!$L$5:$L$88>$A11)) -> 0 | J11: =SUMPRODUCT((Costos!$C$5:$C$88=J$4)*Costos!$E$5:$E$88*(Costos!$K$5:$K$88<=$A11)*(Costos!$L$5:$L$88>$A11)) -> 0 | ... N11: =SUMPRODUCT((Costos!$C$5:$C$88=N$4)*Costos!$E$5:$E$88*(Costos!$K$5:$K$88<=$A11)*(Costos!$L$5:$L$88>$A11)) -> 0
A12: 7 | B12: =INDEX(Calendario!$B$3:$B$172,A12+1) -> 46308 | C12: =SUMPRODUCT((Costos!$C$5:$C$88=C$4)*Costos!$E$5:$E$88*(Costos!$K$5:$K$88<=$A12)*(Costos!$L$5:$L$88>$A12)) -> 0.8 | D12: =SUMPRODUCT((Costos!$C$5:$C$88=D$4)*Costos!$E$5:$E$88*(Costos!$K$5:$K$88<=$A12)*(Costos!$L$5:$L$88>$A12)) -> 0.2 | E12: =SUMPRODUCT((Costos!$C$5:$C$88=E$4)*Costos!$E$5:$E$88*(Costos!$K$5:$K$88<=$A12)*(Costos!$L$5:$L$88>$A12)) -> 0 | F12: =SUMPRODUCT((Costos!$C$5:$C$88=F$4)*Costos!$E$5:$E$88*(Costos!$K$5:$K$88<=$A12)*(Costos!$L$5:$L$88>$A12)) -> 0 | G12: =SUMPRODUCT((Costos!$C$5:$C$88=G$4)*Costos!$E$5:$E$88*(Costos!$K$5:$K$88<=$A12)*(Costos!$L$5:$L$88>$A12)) -> 0 | H12: =SUMPRODUCT((Costos!$C$5:$C$88=H$4)*Costos!$E$5:$E$88*(Costos!$K$5:$K$88<=$A12)*(Costos!$L$5:$L$88>$A12)) -> 0 | I12: =SUMPRODUCT((Costos!$C$5:$C$88=I$4)*Costos!$E$5:$E$88*(Costos!$K$5:$K$88<=$A12)*(Costos!$L$5:$L$88>$A12)) -> 0 | J12: =SUMPRODUCT((Costos!$C$5:$C$88=J$4)*Costos!$E$5:$E$88*(Costos!$K$5:$K$88<=$A12)*(Costos!$L$5:$L$88>$A12)) -> 1 | ... N12: =SUMPRODUCT((Costos!$C$5:$C$88=N$4)*Costos!$E$5:$E$88*(Costos!$K$5:$K$88<=$A12)*(Costos!$L$5:$L$88>$A12)) -> 0
A13: 8 | B13: =INDEX(Calendario!$B$3:$B$172,A13+1) -> 46309 | C13: =SUMPRODUCT((Costos!$C$5:$C$88=C$4)*Costos!$E$5:$E$88*(Costos!$K$5:$K$88<=$A13)*(Costos!$L$5:$L$88>$A13)) -> 0.7 | D13: =SUMPRODUCT((Costos!$C$5:$C$88=D$4)*Costos!$E$5:$E$88*(Costos!$K$5:$K$88<=$A13)*(Costos!$L$5:$L$88>$A13)) -> 1 | E13: =SUMPRODUCT((Costos!$C$5:$C$88=E$4)*Costos!$E$5:$E$88*(Costos!$K$5:$K$88<=$A13)*(Costos!$L$5:$L$88>$A13)) -> 0 | F13: =SUMPRODUCT((Costos!$C$5:$C$88=F$4)*Costos!$E$5:$E$88*(Costos!$K$5:$K$88<=$A13)*(Costos!$L$5:$L$88>$A13)) -> 0 | G13: =SUMPRODUCT((Costos!$C$5:$C$88=G$4)*Costos!$E$5:$E$88*(Costos!$K$5:$K$88<=$A13)*(Costos!$L$5:$L$88>$A13)) -> 0.2 | H13: =SUMPRODUCT((Costos!$C$5:$C$88=H$4)*Costos!$E$5:$E$88*(Costos!$K$5:$K$88<=$A13)*(Costos!$L$5:$L$88>$A13)) -> 2 | I13: =SUMPRODUCT((Costos!$C$5:$C$88=I$4)*Costos!$E$5:$E$88*(Costos!$K$5:$K$88<=$A13)*(Costos!$L$5:$L$88>$A13)) -> 0.8 | J13: =SUMPRODUCT((Costos!$C$5:$C$88=J$4)*Costos!$E$5:$E$88*(Costos!$K$5:$K$88<=$A13)*(Costos!$L$5:$L$88>$A13)) -> 1 | ... N13: =SUMPRODUCT((Costos!$C$5:$C$88=N$4)*Costos!$E$5:$E$88*(Costos!$K$5:$K$88<=$A13)*(Costos!$L$5:$L$88>$A13)) -> 0
A14: 9 | B14: =INDEX(Calendario!$B$3:$B$172,A14+1) -> 46310 | C14: =SUMPRODUCT((Costos!$C$5:$C$88=C$4)*Costos!$E$5:$E$88*(Costos!$K$5:$K$88<=$A14)*(Costos!$L$5:$L$88>$A14)) -> 0.7 | D14: =SUMPRODUCT((Costos!$C$5:$C$88=D$4)*Costos!$E$5:$E$88*(Costos!$K$5:$K$88<=$A14)*(Costos!$L$5:$L$88>$A14)) -> 1 | E14: =SUMPRODUCT((Costos!$C$5:$C$88=E$4)*Costos!$E$5:$E$88*(Costos!$K$5:$K$88<=$A14)*(Costos!$L$5:$L$88>$A14)) -> 0 | F14: =SUMPRODUCT((Costos!$C$5:$C$88=F$4)*Costos!$E$5:$E$88*(Costos!$K$5:$K$88<=$A14)*(Costos!$L$5:$L$88>$A14)) -> 0 | G14: =SUMPRODUCT((Costos!$C$5:$C$88=G$4)*Costos!$E$5:$E$88*(Costos!$K$5:$K$88<=$A14)*(Costos!$L$5:$L$88>$A14)) -> 0.2 | H14: =SUMPRODUCT((Costos!$C$5:$C$88=H$4)*Costos!$E$5:$E$88*(Costos!$K$5:$K$88<=$A14)*(Costos!$L$5:$L$88>$A14)) -> 2 | I14: =SUMPRODUCT((Costos!$C$5:$C$88=I$4)*Costos!$E$5:$E$88*(Costos!$K$5:$K$88<=$A14)*(Costos!$L$5:$L$88>$A14)) -> 0.8 | J14: =SUMPRODUCT((Costos!$C$5:$C$88=J$4)*Costos!$E$5:$E$88*(Costos!$K$5:$K$88<=$A14)*(Costos!$L$5:$L$88>$A14)) -> 1 | ... N14: =SUMPRODUCT((Costos!$C$5:$C$88=N$4)*Costos!$E$5:$E$88*(Costos!$K$5:$K$88<=$A14)*(Costos!$L$5:$L$88>$A14)) -> 0
A15: 10 | B15: =INDEX(Calendario!$B$3:$B$172,A15+1) -> 46311 | C15: =SUMPRODUCT((Costos!$C$5:$C$88=C$4)*Costos!$E$5:$E$88*(Costos!$K$5:$K$88<=$A15)*(Costos!$L$5:$L$88>$A15)) -> 0.7 | D15: =SUMPRODUCT((Costos!$C$5:$C$88=D$4)*Costos!$E$5:$E$88*(Costos!$K$5:$K$88<=$A15)*(Costos!$L$5:$L$88>$A15)) -> 1 | E15: =SUMPRODUCT((Costos!$C$5:$C$88=E$4)*Costos!$E$5:$E$88*(Costos!$K$5:$K$88<=$A15)*(Costos!$L$5:$L$88>$A15)) -> 0 | F15: =SUMPRODUCT((Costos!$C$5:$C$88=F$4)*Costos!$E$5:$E$88*(Costos!$K$5:$K$88<=$A15)*(Costos!$L$5:$L$88>$A15)) -> 0 | G15: =SUMPRODUCT((Costos!$C$5:$C$88=G$4)*Costos!$E$5:$E$88*(Costos!$K$5:$K$88<=$A15)*(Costos!$L$5:$L$88>$A15)) -> 0.2 | H15: =SUMPRODUCT((Costos!$C$5:$C$88=H$4)*Costos!$E$5:$E$88*(Costos!$K$5:$K$88<=$A15)*(Costos!$L$5:$L$88>$A15)) -> 2 | I15: =SUMPRODUCT((Costos!$C$5:$C$88=I$4)*Costos!$E$5:$E$88*(Costos!$K$5:$K$88<=$A15)*(Costos!$L$5:$L$88>$A15)) -> 0.8 | J15: =SUMPRODUCT((Costos!$C$5:$C$88=J$4)*Costos!$E$5:$E$88*(Costos!$K$5:$K$88<=$A15)*(Costos!$L$5:$L$88>$A15)) -> 1 | ... N15: =SUMPRODUCT((Costos!$C$5:$C$88=N$4)*Costos!$E$5:$E$88*(Costos!$K$5:$K$88<=$A15)*(Costos!$L$5:$L$88>$A15)) -> 0
A16: 11 | B16: =INDEX(Calendario!$B$3:$B$172,A16+1) -> 46314 | C16: =SUMPRODUCT((Costos!$C$5:$C$88=C$4)*Costos!$E$5:$E$88*(Costos!$K$5:$K$88<=$A16)*(Costos!$L$5:$L$88>$A16)) -> 0.7 | D16: =SUMPRODUCT((Costos!$C$5:$C$88=D$4)*Costos!$E$5:$E$88*(Costos!$K$5:$K$88<=$A16)*(Costos!$L$5:$L$88>$A16)) -> 1 | E16: =SUMPRODUCT((Costos!$C$5:$C$88=E$4)*Costos!$E$5:$E$88*(Costos!$K$5:$K$88<=$A16)*(Costos!$L$5:$L$88>$A16)) -> 0 | F16: =SUMPRODUCT((Costos!$C$5:$C$88=F$4)*Costos!$E$5:$E$88*(Costos!$K$5:$K$88<=$A16)*(Costos!$L$5:$L$88>$A16)) -> 0 | G16: =SUMPRODUCT((Costos!$C$5:$C$88=G$4)*Costos!$E$5:$E$88*(Costos!$K$5:$K$88<=$A16)*(Costos!$L$5:$L$88>$A16)) -> 0.2 | H16: =SUMPRODUCT((Costos!$C$5:$C$88=H$4)*Costos!$E$5:$E$88*(Costos!$K$5:$K$88<=$A16)*(Costos!$L$5:$L$88>$A16)) -> 2 | I16: =SUMPRODUCT((Costos!$C$5:$C$88=I$4)*Costos!$E$5:$E$88*(Costos!$K$5:$K$88<=$A16)*(Costos!$L$5:$L$88>$A16)) -> 0.8 | J16: =SUMPRODUCT((Costos!$C$5:$C$88=J$4)*Costos!$E$5:$E$88*(Costos!$K$5:$K$88<=$A16)*(Costos!$L$5:$L$88>$A16)) -> 1 | ... N16: =SUMPRODUCT((Costos!$C$5:$C$88=N$4)*Costos!$E$5:$E$88*(Costos!$K$5:$K$88<=$A16)*(Costos!$L$5:$L$88>$A16)) -> 0
... A144: 139 | B144: =INDEX(Calendario!$B$3:$B$172,A144+1) -> 46507 | C144: =SUMPRODUCT((Costos!$C$5:$C$88=C$4)*Costos!$E$5:$E$88*(Costos!$K$5:$K$88<=$A144)*(Costos!$L$5:$L$88>$A144)) -> 0.8 | D144: =SUMPRODUCT((Costos!$C$5:$C$88=D$4)*Costos!$E$5:$E$88*(Costos!$K$5:$K$88<=$A144)*(Costos!$L$5:$L$88>$A144)) -> 0.6 | E144: =SUMPRODUCT((Costos!$C$5:$C$88=E$4)*Costos!$E$5:$E$88*(Costos!$K$5:$K$88<=$A144)*(Costos!$L$5:$L$88>$A144)) -> 0 | F144: =SUMPRODUCT((Costos!$C$5:$C$88=F$4)*Costos!$E$5:$E$88*(Costos!$K$5:$K$88<=$A144)*(Costos!$L$5:$L$88>$A144)) -> 0.5 | G144: =SUMPRODUCT((Costos!$C$5:$C$88=G$4)*Costos!$E$5:$E$88*(Costos!$K$5:$K$88<=$A144)*(Costos!$L$5:$L$88>$A144)) -> 0 | H144: =SUMPRODUCT((Costos!$C$5:$C$88=H$4)*Costos!$E$5:$E$88*(Costos!$K$5:$K$88<=$A144)*(Costos!$L$5:$L$88>$A144)) -> 0 | I144: =SUMPRODUCT((Costos!$C$5:$C$88=I$4)*Costos!$E$5:$E$88*(Costos!$K$5:$K$88<=$A144)*(Costos!$L$5:$L$88>$A144)) -> 0 | J144: =SUMPRODUCT((Costos!$C$5:$C$88=J$4)*Costos!$E$5:$E$88*(Costos!$K$5:$K$88<=$A144)*(Costos!$L$5:$L$88>$A144)) -> 0 | ... N144: =SUMPRODUCT((Costos!$C$5:$C$88=N$4)*Costos!$E$5:$E$88*(Costos!$K$5:$K$88<=$A144)*(Costos!$L$5:$L$88>$A144)) -> 0
A146: Carga máxima | C146: =MAX(C5:C144) -> 1 | D146: =MAX(D5:D144) -> 1 | E146: =MAX(E5:E144) -> 1 | F146: =MAX(F5:F144) -> 2 | G146: =MAX(G5:G144) -> 1 | H146: =MAX(H5:H144) -> 2 | I146: =MAX(I5:I144) -> 1 | J146: =MAX(J5:J144) -> 1 | ... N146: =MAX(N5:N144) -> 5.625
A148: Control | C148: =IF(C146<=C$3+0.0001,"OK","SOBRECARGA") -> OK | D148: =IF(D146<=D$3+0.0001,"OK","SOBRECARGA") -> OK | E148: =IF(E146<=E$3+0.0001,"OK","SOBRECARGA") -> OK | F148: =IF(F146<=F$3+0.0001,"OK","SOBRECARGA") -> OK | G148: =IF(G146<=G$3+0.0001,"OK","SOBRECARGA") -> OK | H148: =IF(H146<=H$3+0.0001,"OK","SOBRECARGA") -> OK | I148: =IF(I146<=I$3+0.0001,"OK","SOBRECARGA") -> OK | J148: =IF(J146<=J$3+0.0001,"OK","SOBRECARGA") -> OK | ... L148: =IF(L146<=L$3+0.0001,"OK","SOBRECARGA") -> OK | M148: =IF(SUMPRODUCT(--(M5:M144>IF($B$5:$B$144<VentanaDesde,M$3,1)+0.0001))=0,"OK","SOBRECARGA") -> OK | N148: =IF(N146<=N$3+0.0001,"OK","SOBRECARGA") -> OK
A150: RR.HH.: capacidad 0,5 FTE hasta el 31/12/2026 y 1,0 FTE desde el 01/01/2027 (restricción R-6, meses 4 a 7).

Sheet Recursos
A1: Recursos, tarifas y capacidad
A2: Tarifas de venta de Tandem: supuesto de mercado regional (USD por día hábil), a validar contra la lista de precios del contrato. Los recursos de VCA se valorizan a costo interno cargado. Las categorías corresponden a las líneas del costo base de la N1.
A4: Código | B4: Recurso | C4: Línea de costo (N1) | D4: Tarifa USD/día | E4: Capacidad (FTE) | F4: Observación
A5: PM | B5: Project Manager (Tandem) | C5: Equipo Tandem | D5: 520 | E5: 1 | F5: Dedicado; responsable de la línea base.
A6: PO | B6: Product Owner (Tandem) | C6: Equipo Tandem | D6: 480 | E6: 1 | F6: Carolina Méndez.
A7: UX | B7: Diseñador/a UX/UI (Tandem) | C7: Equipo Tandem | D7: 420 | E7: 1 | F7: Diseño y revisión de interfaces.
A8: DEV | B8: Desarrollador/a full-stack (Tandem) | C8: Equipo Tandem | D8: 440 | E8: 2 | F8: 2 desarrolladores full-stack (N1).
A9: QA | B9: Especialista QA (Tandem) | C9: Equipo Tandem | D9: 360 | E9: 1 | F9: Especialista QA (N1).
A10: INT | B10: Ingeniero/a de integraciones (Tandem) | C10: Integraciones | D10: 480 | E10: 2 | F10: Especialistas de integración de Tandem (línea Integraciones de la N1); equipo de 2.
A11: OPS | B11: Ingeniero/a DevOps (Tandem) | C11: Ambientes | D11: 460 | E11: 1 | F11: Ambientes, migración y despliegue.
A12: CAM | B12: Consultor/a de gestión del cambio (Tandem) | C12: Gestión del cambio | D12: 400 | E12: 1 | F12: Consultor/a de cambio; complementa al referente de RR.HH.
A13: TEC | B13: Tecnología VCA (P. Guzmán) | C13: Horas VCA | D13: 190 | E13: 0.5 | F13: Pablo Guzmán; máximo 0,5 FTE (R-6).
A14: SG | B14: Servicios Generales VCA (D. Sosa) | C14: Horas VCA | D14: 170 | E14: 0.5 | F14: Damián Sosa; máximo 0,5 FTE (R-6).
A15: RH | B15: RR.HH. VCA (S. Ibarra / referente) | C15: Horas VCA | D15: 160 | E15: 0.5 | F15: Soledad Ibarra / referente; 0,5 FTE hasta dic-26 y 1,0 FTE de ene a abr-27 (R-6).
A16: USR | B16: Usuarios de prueba UAT (VCA) | C16: Horas VCA | D16: 150 | E16: 99 | F16: 120 colaboradores de VCA en sesiones de prueba.

Sheet Parámetros
A1: Parámetros del modelo — WKH-2026 · Entrega N2
A2: Azul = dato de entrada editable · negro = fórmula · verde = vínculo a otra hoja. Todo el modelo se recalcula desde estas celdas, las hojas Tareas y Costos.
A3: Parámetro | B3: Valor | C3: Fuente / nota
A4: Inicio del proyecto (H-0, firma del Acta) | B4: 46296 | C4: Acta de constitución, hito H-0 (N1).
A5: Ventana de cierre de balances de VCA — desde | B5: 46388 | C5: Restricción R-3 de la N1: sin despliegue masivo ni capacitación.
A6: Ventana de cierre de balances de VCA — hasta | B6: 46461 | C6: Ídem. La UAT puede empezar el 16/03.
A7: Reserva para contingencias (USD) | B7: 22000 | C7: Definida en la N1 (5,5 % del costo base descendente). Cubre riesgos identificados; se detalla en el registro de riesgos (N3/N4).
A8: Reserva de gestión (% sobre la línea base) | B8: 0.04 | C8: PMBOK 7. Fuera de la línea base; la libera el Comité de Inversiones mediante solicitud de cambio.
A9: Tolerancia de control (±) | B9: 0.1 | C9: Acta (N1), OP-1 y R-1. Es un margen de desvío, no una reserva.
A10: Presupuesto autorizado en el Acta (USD) | B10: 420000 | C10: Acta de constitución (N1): techo de autorización y base de la banda de tolerancia hasta la ratificación en H-1.
A11: Costo base descendente de la N1 (USD) | B11: 398000 | C11: N1, sección 4.3: USD 398.000 de conceptos base + USD 22.000 de contingencia = USD 420.000.
A12: Solape 2.1 → 2.3: inicio a inicio (días hábiles) | B12: 5 | C12: Fast-tracking: el módulo de escritorios arranca con las reglas de reserva ya relevadas (primera semana de 2.1).
A13: Solape 2.6 → 3.5: inicio a inicio (días hábiles) | B13: 10 | C13: Las pruebas de integración y carga arrancan con 10 días de avance de notificaciones.
A14: Solape 5.4 → 5.5 y 5.6: fin a fin (días hábiles) | B14: 2 | C14: Tablero e informe se cierran 2 días después de terminar la estabilización.
A15: Desfase 5.3 → 5.4: final a inicio (días hábiles) | B15: 4 | C15: Correcciones post-UAT, capacitación masiva a usuarios y ensayo de corte; 24, 25 y 26/03 no son laborables. Go-live el 31/03.
... A18: Horas por usuario de prueba | B18: 1.5 | C18: Supuesto: una sesión guiada de 90 minutos.
A20: Feriados y días no laborables (excluidos del calendario)
A21: Fecha | B21: Descripción
A22: 46307 | B22: Día del Respeto a la Diversidad Cultural
A23: 46349 | B23: Día de la Soberanía Nacional (trasladado)
A24: 46363 | B24: Día no laborable con fines turísticos (puente)
A25: 46364 | B25: Inmaculada Concepción de María
A26: 46381 | B26: Navidad
A27: 46388 | B27: Año Nuevo
A28: 46426 | B28: Carnaval
A29: 46427 | B29: Carnaval
A30: 46470 | B30: Día de la Memoria
A31: 46471 | B31: Jueves Santo (no laborable)
A32: 46472 | B32: Viernes Santo
A33: 46479 | B33: Día del Veterano y de los Caídos en Malvinas
A35: Supuesto: los feriados y traslados 2026-2027 se cargaron manualmente y deben validarse contra el calendario oficial y el de VCA. Para agregar uno, insertar una fila dentro del rango.

Sheet Calendario
A1: Calendario laboral del proyecto (lunes a viernes sin feriados). Índice 0 = H-0.
A2: Índice | B2: Fecha
A3: 0 | B3: =InicioProyecto -> 46296
A4: 1 | B4: =WORKDAY(B3,1,Feriados) -> 46297
A5: 2 | B5: =WORKDAY(B4,1,Feriados) -> 46300
A6: 3 | B6: =WORKDAY(B5,1,Feriados) -> 46301
A7: 4 | B7: =WORKDAY(B6,1,Feriados) -> 46302
A8: 5 | B8: =WORKDAY(B7,1,Feriados) -> 46303
A9: 6 | B9: =WORKDAY(B8,1,Feriados) -> 46304
A10: 7 | B10: =WORKDAY(B9,1,Feriados) -> 46308
A11: 8 | B11: =WORKDAY(B10,1,Feriados) -> 46309
A12: 9 | B12: =WORKDAY(B11,1,Feriados) -> 46310
A13: 10 | B13: =WORKDAY(B12,1,Feriados) -> 46311
A14: 11 | B14: =WORKDAY(B13,1,Feriados) -> 46314
A15: 12 | B15: =WORKDAY(B14,1,Feriados) -> 46315
... A172: 169 | B172: =WORKDAY(B171,1,Feriados) -> 46549
